{"label": "5/4~10", "prev_label": "5/4~10", "ref_date": "2026-05-10", "summary": {"spend": 16228383, "impressions": 733022, "clicks": 18198, "purchases": 360, "revenue": 142598217, "roas_pct": 878.7, "avg_ctr": 2.79, "avg_cpc": 1034.0, "active_ads": 115, "winning_thresholds": {"avg_roas": 8.683, "avg_roas_pct": 868.3, "avg_ctr": 2.26, "avg_cvr": 2.53, "avg_cpc": 1091.0, "avg_purchases": 10.7, "tc_avg_ctr": 2.79}}, "prev_summary": {"spend": 16228383, "revenue": 142598217, "roas_pct": 878.7, "purchases": 360, "impressions": 733022, "clicks": 18198, "avg_ctr": 2.79, "avg_cpc": 0, "active_ads": 115}, "trends": {"spend_up": [], "rev_up": [], "cpc_eff_up": [], "conv_dn": [], "cpc_eff_dn": []}, "pie": {}, "winning": [{"key": "전환_파트너스_po0ong_플랩", "base_key": "파트너스_po0ong", "ad_id": "120243392317660667", "objective": "전환", "pa_type": "PA", "landing": "플랩", "purpose": "전환", "mgr": "파트너스", "media": "영상", "spend": 2200908, "impressions": 75900, "clicks": 2465, "purchases": 44.0, "revenue": 17685106, "age_days": 111, "roas": 8.035368, "roas_pct": 804.0, "ctr": 3.25, "cvr": 1.78, "cpc": 893.0, "is_new": false, "old_roas_pct": 804.0, "roas_delta": 0.0, "prev_spend": 2200908, "prev_ctr": 3.25, "prev_cvr": 1.78, "prev_cpc": 893.0, "prev_purchases": 44, "prev_revenue": 17685106, "img": null, "img_type": "video", "video": "821315101048750", "win_score": 3, "win_type": "전환", "win_flags": {"roas": false, "ctr": true, "cvr": false, "cpc": true, "purchases": true}}, {"key": "전환_26인치_재입고01_콜리_오딧", "base_key": "26인치_재입고01_콜리", "ad_id": "120248577076990667", "objective": "전환", "pa_type": "자컨", "landing": "오딧", "purpose": "전환", "mgr": "콜리", "media": "영상", "spend": 1351940, "impressions": 71837, "clicks": 1316, "purchases": 34.0, "revenue": 13448800, "age_days": 4, "roas": 9.947779, "roas_pct": 995.0, "ctr": 1.83, "cvr": 2.58, "cpc": 1027.0, "is_new": true, "old_roas_pct": 995.0, "roas_delta": 0.0, "prev_spend": 1351940, "prev_ctr": 1.83, "prev_cvr": 2.58, "prev_cpc": 1027.0, "prev_purchases": 34, "prev_revenue": 13448800, "img": "https://www.facebook.com/ads/image/?d=AQL6K28zg5wS4JKBsHZD0vncQKAuwcSw-IFUAJj37jKoDw71rAX3-FfUNYOsbf3duH3th26KUoOc4YpiltSZqX3OXjn2cDpQMez-EKVOoOTtRYZragm6y4gOQe19mbSyPW8oZWPvjaw12EDvtP5FpeUv", "img_type": "video", "video": "1893787557939918", "win_score": 4, "win_type": "전환", "win_flags": {"roas": true, "ctr": false, "cvr": true, "cpc": true, "purchases": true}}, {"key": "전환_펄스레드_파트너스_소진_오딧", "base_key": "펄스레드_파트너스_소진", "ad_id": "120243398583140667", "objective": "전환", "pa_type": "PA", "landing": "오딧", "purpose": "전환", "mgr": "파트너스", "media": "영상", "spend": 2217301, "impressions": 88731, "clicks": 2699, "purchases": 29.0, "revenue": 11815300, "age_days": 96, "roas": 5.328686, "roas_pct": 533.0, "ctr": 3.04, "cvr": 1.07, "cpc": 822.0, "is_new": false, "old_roas_pct": 533.0, "roas_delta": 0.0, "prev_spend": 2217301, "prev_ctr": 3.04, "prev_cvr": 1.07, "prev_cpc": 822.0, "prev_purchases": 29, "prev_revenue": 11815300, "img": null, "img_type": "video", "video": "1932103937427171", "win_score": 3, "win_type": "전환", "win_flags": {"roas": false, "ctr": true, "cvr": false, "cpc": true, "purchases": true}}, {"key": "전환_오딧+플랩_파트너스_밍똥_오딧", "base_key": "오딧+플랩_파트너스_밍똥", "ad_id": "120247132341220667", "objective": "전환", "pa_type": "PA", "landing": "오딧", "purpose": "전환", "mgr": "파트너스", "media": "영상", "spend": 1597374, "impressions": 97205, "clicks": 2664, "purchases": 28.0, "revenue": 10745300, "age_days": 26, "roas": 6.726853, "roas_pct": 673.0, "ctr": 2.74, "cvr": 1.05, "cpc": 600.0, "is_new": false, "old_roas_pct": 673.0, "roas_delta": 0.0, "prev_spend": 1597374, "prev_ctr": 2.74, "prev_cvr": 1.05, "prev_cpc": 600.0, "prev_purchases": 28, "prev_revenue": 10745300, "img": null, "img_type": "video", "video": "1681610669498118", "win_score": 3, "win_type": "전환", "win_flags": {"roas": false, "ctr": true, "cvr": false, "cpc": true, "purchases": true}}, {"key": "전환_펄스레드재입고03_콜리_오딧", "base_key": "펄스레드재입고03_콜리", "ad_id": "120247747183630667", "objective": "전환", "pa_type": "자컨", "landing": "오딧", "purpose": "전환", "mgr": "콜리", "media": "배너", "spend": 604954, "impressions": 27554, "clicks": 654, "purchases": 24.0, "revenue": 10246335, "age_days": 16, "roas": 16.937379, "roas_pct": 1694.0, "ctr": 2.37, "cvr": 3.67, "cpc": 925.0, "is_new": false, "old_roas_pct": 1694.0, "roas_delta": 0.0, "prev_spend": 604954, "prev_ctr": 2.37, "prev_cvr": 3.67, "prev_cpc": 925.0, "prev_purchases": 24, "prev_revenue": 10246335, "img": "https://scontent-sin11-1.xx.fbcdn.net/v/t45.1600-4/677693950_122109805701123564_297151026179670161_n.png?stp=dst-jpg_tt6&_nc_cat=104&ccb=1-7&_nc_sid=d5bd00&_nc_ohc=QpJiHs6UUrsQ7kNvwHxQALZ&_nc_oc=Adpsvgz5T-aJMfJtdIUALY-ZOqKZcciINLPbcDOxJY_qY-P4sWTj0JM5QhAZQ-sQU44&_nc_zt=1&_nc_ht=scontent-sin11-1.xx&edm=AAwGEdEEAAAA&_nc_gid=ffPPi6QV_CD7WHtTbS8f4g&_nc_tpa=Q5bMBQF_ykso6qZPnXsETbKLCTF-BKb2IJoXv4oJgv8-7VYMAH55PEUpubgWuUuTOJvAR-yNuoHtVBkE3g&oh=00_Af9hqY4xWQas5IGT5qlfw04mF25s94SqEjAuGNx4kGUhSw&oe=6A370297", "img_type": "img", "video": null, "win_score": 5, "win_type": "전환", "win_flags": {"roas": true, "ctr": true, "cvr": true, "cpc": true, "purchases": true}}, {"key": "전환_26인치_재입고01-1_콜리_오딧", "base_key": "26인치_재입고01-1_콜리", "ad_id": "120248577077010667", "objective": "전환", "pa_type": "자컨", "landing": "오딧", "purpose": "전환", "mgr": "콜리", "media": "영상", "spend": 401993, "impressions": 15414, "clicks": 359, "purchases": 21.0, "revenue": 8526900, "age_days": 4, "roas": 21.211563, "roas_pct": 2121.0, "ctr": 2.33, "cvr": 5.85, "cpc": 1120.0, "is_new": true, "old_roas_pct": 2121.0, "roas_delta": 0.0, "prev_spend": 401993, "prev_ctr": 2.33, "prev_cvr": 5.85, "prev_cpc": 1120.0, "prev_purchases": 21, "prev_revenue": 8526900, "img": "https://www.facebook.com/ads/image/?d=AQIUzJmjpkaUEeAyYn01KF01yfK0sz9QHBgUBh71R3XnuRXVf1imdcrEJY0-kcc7a3TtYbR7M60_8YDbDTPMNExUOreu5MaRPbVaKdiiJQUe-eEd3b_WrSylNtDHK3QuSG2F-rJsbvmippZHK_FLx4kE", "img_type": "video", "video": "1522790255928346", "win_score": 4, "win_type": "전환", "win_flags": {"roas": true, "ctr": true, "cvr": true, "cpc": false, "purchases": true}}, {"key": "전환_오딧+플랩_파트너스_나나_오딧", "base_key": "오딧+플랩_파트너스_나나", "ad_id": "120247265165380667", "objective": "전환", "pa_type": "PA", "landing": "오딧", "purpose": "전환", "mgr": "파트너스", "media": "영상", "spend": 620937, "impressions": 34878, "clicks": 1070, "purchases": 16.0, "revenue": 5868900, "age_days": 24, "roas": 9.451684, "roas_pct": 945.0, "ctr": 3.07, "cvr": 1.5, "cpc": 580.0, "is_new": false, "old_roas_pct": 945.0, "roas_delta": 0.0, "prev_spend": 620937, "prev_ctr": 3.07, "prev_cvr": 1.5, "prev_cpc": 580.0, "prev_purchases": 16, "prev_revenue": 5868900, "img": null, "img_type": "video", "video": "1518469182978189", "win_score": 4, "win_type": "전환", "win_flags": {"roas": true, "ctr": true, "cvr": false, "cpc": true, "purchases": true}}, {"key": "전환_오딧재입고02_콜리_오딧", "base_key": "오딧재입고02_콜리", "ad_id": "120247693697390667", "objective": "전환", "pa_type": "자컨", "landing": "오딧", "purpose": "전환", "mgr": "콜리", "media": "배너", "spend": 651897, "impressions": 30683, "clicks": 664, "purchases": 15.0, "revenue": 5810527, "age_days": 17, "roas": 8.913259, "roas_pct": 891.0, "ctr": 2.16, "cvr": 2.26, "cpc": 982.0, "is_new": false, "old_roas_pct": 891.0, "roas_delta": 0.0, "prev_spend": 651897, "prev_ctr": 2.16, "prev_cvr": 2.26, "prev_cpc": 982.0, "prev_purchases": 15, "prev_revenue": 5810527, "img": "https://scontent-sin6-3.xx.fbcdn.net/v/t45.1600-4/676526023_122109712401123564_1460242989174341096_n.png?stp=dst-jpg_tt6&_nc_cat=110&ccb=1-7&_nc_sid=d5bd00&_nc_ohc=sDnhRzabuJsQ7kNvwGgLEOg&_nc_oc=AdqlrQzQBtp4iMlJg1YFtNXskSeRc80d7k7z_c2sSdKAIjpM7GXAfUhtCQCVbxK5DVE&_nc_zt=1&_nc_ht=scontent-sin6-3.xx&edm=AAwGEdEEAAAA&_nc_gid=5UZxNZvyZBM8SPh51RHmCg&_nc_tpa=Q5bMBQHfHQLhOhcwDg477m655oiquqij8ppS5DOqMOfMPsrSCCg8V-pBU3F5eT6skIYgRGQlQHil6JT85w&oh=00_Af96fBmdr0vrqvTUT46Xe6kGWMGkb1IRw9vK98uadNW2SQ&oe=6A36FB81", "img_type": "img", "video": null, "win_score": 3, "win_type": "전환", "win_flags": {"roas": true, "ctr": false, "cvr": false, "cpc": true, "purchases": true}}, {"key": "전환_펄스레드_컬러01_세레나_오딧", "base_key": "펄스레드_컬러01_세레나", "ad_id": "120244507767160667", "objective": "전환", "pa_type": "자컨", "landing": "오딧", "purpose": "전환", "mgr": "세레나", "media": "영상", "spend": 342146, "impressions": 14796, "clicks": 411, "purchases": 8.0, "revenue": 4246000, "age_days": 72, "roas": 12.409907, "roas_pct": 1241.0, "ctr": 2.78, "cvr": 1.95, "cpc": 832.0, "is_new": false, "old_roas_pct": 1241.0, "roas_delta": 0.0, "prev_spend": 342146, "prev_ctr": 2.78, "prev_cvr": 1.95, "prev_cpc": 832.0, "prev_purchases": 8, "prev_revenue": 4246000, "img": "https://www.facebook.com/ads/image/?d=AQICdo05fLB-OvhqicYXFzenGxnDaHn_EiTzL5sd2gynwzwggaiXz9yfnVTlkrvaQnRn7qajwzdVU7BCP0wvbJvPxeRzPw2U40sXFtzZIiFbrWh1xlUBcrvVVByqCcjUNmUVaMF0-xbSDb5CELEsmLkq", "img_type": "video", "video": "1240583091622496", "win_score": 3, "win_type": "전환", "win_flags": {"roas": true, "ctr": true, "cvr": false, "cpc": true, "purchases": false}}, {"key": "전환_솔티브랜드02_리지_플랩", "base_key": "솔티브랜드02_리지", "ad_id": "120248695560000667", "objective": "전환", "pa_type": "자컨", "landing": "플랩", "purpose": "전환", "mgr": "리지", "media": "배너", "spend": 343758, "impressions": 12072, "clicks": 422, "purchases": 8.0, "revenue": 3327200, "age_days": 3, "roas": 9.678902, "roas_pct": 968.0, "ctr": 3.5, "cvr": 1.9, "cpc": 815.0, "is_new": true, "old_roas_pct": 968.0, "roas_delta": 0.0, "prev_spend": 343758, "prev_ctr": 3.5, "prev_cvr": 1.9, "prev_cpc": 815.0, "prev_purchases": 8, "prev_revenue": 3327200, "img": "https://scontent-sin11-1.xx.fbcdn.net/v/t45.1600-4/691806695_122101476549297071_6523363003118697610_n.png?stp=dst-jpg_tt6&_nc_cat=105&ccb=1-7&_nc_sid=d5bd00&_nc_ohc=rdcIUtgpCrUQ7kNvwEbE2z4&_nc_oc=AdqwG0qgltQeCTrwG4KkXcsz45DKdwsENXQnKboSwZPk2zbPnP3as3IO-YbvJNUL1l8&_nc_zt=1&_nc_ht=scontent-sin11-1.xx&edm=AAwGEdEEAAAA&_nc_gid=2AfidITGas9_-uch8QcHgA&_nc_tpa=Q5bMBQHlsg9LTFeFFOZ5Mdqj1YvjH3by-G1GRr3ablWIIX4Ux4qHbHMHunOd68O7bRAt-xGPC5OOcuoqsg&oh=00_Af8NfJ3aMA4_KRR_NLMNZTK2hHOUY2cN7Or5HiGfnvxFkQ&oe=6A36D6C2", "img_type": "img", "video": null, "win_score": 3, "win_type": "전환", "win_flags": {"roas": true, "ctr": true, "cvr": false, "cpc": true, "purchases": false}}], "d7_win": [{"key": "전환_26인치_재입고01-1_콜리_오딧", "base_key": "26인치_재입고01-1_콜리", "ad_id": "120248577077010667", "objective": "전환", "pa_type": "자컨", "landing": "오딧", "purpose": "전환", "mgr": "콜리", "media": "영상", "spend": 401993, "impressions": 15414, "clicks": 359, "purchases": 21.0, "revenue": 8526900, "age_days": 4, "roas": 21.211563, "roas_pct": 2121.0, "ctr": 2.33, "cvr": 5.85, "cpc": 1120.0, "is_new": true, "old_roas_pct": 2121.0, "roas_delta": 0.0, "prev_spend": 401993, "prev_ctr": 2.33, "prev_cvr": 5.85, "prev_cpc": 1120.0, "prev_purchases": 21, "prev_revenue": 8526900, "img": "https://www.facebook.com/ads/image/?d=AQIUzJmjpkaUEeAyYn01KF01yfK0sz9QHBgUBh71R3XnuRXVf1imdcrEJY0-kcc7a3TtYbR7M60_8YDbDTPMNExUOreu5MaRPbVaKdiiJQUe-eEd3b_WrSylNtDHK3QuSG2F-rJsbvmippZHK_FLx4kE", "img_type": "video", "video": "1522790255928346", "win_score": 4, "win_type": "전환", "win_flags": {"roas": true, "ctr": true, "cvr": true, "cpc": false, "purchases": true}}, {"key": "전환_작누댁2차활용_07-1_세레나_오딧", "base_key": "작누댁2차활용_07-1_세레나", "ad_id": "120248582841460667", "objective": "전환", "pa_type": "자컨", "landing": "오딧", "purpose": "전환", "mgr": "세레나", "media": "영상", "spend": 79824, "impressions": 2462, "clicks": 61, "purchases": 3.0, "revenue": 1355000, "age_days": 4, "roas": 16.974845, "roas_pct": 1697.0, "ctr": 2.48, "cvr": 4.92, "cpc": 1309.0, "is_new": true, "old_roas_pct": 1697.0, "roas_delta": 0.0, "prev_spend": 79824, "prev_ctr": 2.48, "prev_cvr": 4.92, "prev_cpc": 1309.0, "prev_purchases": 3, "prev_revenue": 1355000, "img": "https://www.facebook.com/ads/image/?d=AQJjJ84RolD5d91Q8n7JnIAiynzLmIsRqv1WKaDDZHE4TIHZL3KbIkt6nO-awKlUtuObqw4hXQQAFoTuE8_kRosogdVkCSBiR5Y0zlQs9sRtNHp05JmE60mbIvFZa6sVFfmzT7Am_pSvuDUJkwz1sHXj", "img_type": "video", "video": "2306821976517932", "win_score": null, "win_type": null, "win_flags": {}}, {"key": "전환_26인치_재입고03_콜리_오딧", "base_key": "26인치_재입고03_콜리", "ad_id": "120248577076970667", "objective": "전환", "pa_type": "자컨", "landing": "오딧", "purpose": "전환", "mgr": "콜리", "media": "배너", "spend": 199423, "impressions": 7755, "clicks": 152, "purchases": 10.0, "revenue": 3196000, "age_days": 4, "roas": 16.026236, "roas_pct": 1603.0, "ctr": 1.96, "cvr": 6.58, "cpc": 1312.0, "is_new": true, "old_roas_pct": 1603.0, "roas_delta": 0.0, "prev_spend": 199423, "prev_ctr": 1.96, "prev_cvr": 6.58, "prev_cpc": 1312.0, "prev_purchases": 10, "prev_revenue": 3196000, "img": "https://scontent-sin11-1.xx.fbcdn.net/v/t45.1600-4/686041817_122111127267123564_487314875706961986_n.png?stp=dst-jpg_tt6&_nc_cat=104&ccb=1-7&_nc_sid=d5bd00&_nc_ohc=KGdC8NRHjgAQ7kNvwFSQg2e&_nc_oc=AdoVqzU6zkNJlXQW3fn0qVP7ODLGL4zPCNr_MXSN2r8802ufoZPevdje9584qB5WSzg&_nc_zt=1&_nc_ht=scontent-sin11-1.xx&edm=AAwGEdEEAAAA&_nc_gid=Zu2brkAvDGsELzhzzbdGxQ&_nc_tpa=Q5bMBQG7RY9Nc5xPNodonbgripxp--AkY-b5sc44wb09cJarK7XUdbOAlQ5yQba0nvZBnaYmC6ES1aHprQ&oh=00_Af-o3GsJ9J4IlIgY6pxi9smohqUngmix5aETQdFI1tBHAQ&oe=6A36FF47", "img_type": "img", "video": null, "win_score": 2, "win_type": "전환", "win_flags": {"roas": true, "ctr": false, "cvr": true, "cpc": false, "purchases": false}}, {"key": "전환_26인치_재입고01_콜리_오딧", "base_key": "26인치_재입고01_콜리", "ad_id": "120248577076990667", "objective": "전환", "pa_type": "자컨", "landing": "오딧", "purpose": "전환", "mgr": "콜리", "media": "영상", "spend": 1351940, "impressions": 71837, "clicks": 1316, "purchases": 34.0, "revenue": 13448800, "age_days": 4, "roas": 9.947779, "roas_pct": 995.0, "ctr": 1.83, "cvr": 2.58, "cpc": 1027.0, "is_new": true, "old_roas_pct": 995.0, "roas_delta": 0.0, "prev_spend": 1351940, "prev_ctr": 1.83, "prev_cvr": 2.58, "prev_cpc": 1027.0, "prev_purchases": 34, "prev_revenue": 13448800, "img": "https://www.facebook.com/ads/image/?d=AQL6K28zg5wS4JKBsHZD0vncQKAuwcSw-IFUAJj37jKoDw71rAX3-FfUNYOsbf3duH3th26KUoOc4YpiltSZqX3OXjn2cDpQMez-EKVOoOTtRYZragm6y4gOQe19mbSyPW8oZWPvjaw12EDvtP5FpeUv", "img_type": "video", "video": "1893787557939918", "win_score": 4, "win_type": "전환", "win_flags": {"roas": true, "ctr": false, "cvr": true, "cpc": true, "purchases": true}}, {"key": "전환_솔티브랜드02_리지_플랩", "base_key": "솔티브랜드02_리지", "ad_id": "120248695560000667", "objective": "전환", "pa_type": "자컨", "landing": "플랩", "purpose": "전환", "mgr": "리지", "media": "배너", "spend": 343758, "impressions": 12072, "clicks": 422, "purchases": 8.0, "revenue": 3327200, "age_days": 3, "roas": 9.678902, "roas_pct": 968.0, "ctr": 3.5, "cvr": 1.9, "cpc": 815.0, "is_new": true, "old_roas_pct": 968.0, "roas_delta": 0.0, "prev_spend": 343758, "prev_ctr": 3.5, "prev_cvr": 1.9, "prev_cpc": 815.0, "prev_purchases": 8, "prev_revenue": 3327200, "img": "https://scontent-sin11-1.xx.fbcdn.net/v/t45.1600-4/691806695_122101476549297071_6523363003118697610_n.png?stp=dst-jpg_tt6&_nc_cat=105&ccb=1-7&_nc_sid=d5bd00&_nc_ohc=rdcIUtgpCrUQ7kNvwEbE2z4&_nc_oc=AdqwG0qgltQeCTrwG4KkXcsz45DKdwsENXQnKboSwZPk2zbPnP3as3IO-YbvJNUL1l8&_nc_zt=1&_nc_ht=scontent-sin11-1.xx&edm=AAwGEdEEAAAA&_nc_gid=2AfidITGas9_-uch8QcHgA&_nc_tpa=Q5bMBQHlsg9LTFeFFOZ5Mdqj1YvjH3by-G1GRr3ablWIIX4Ux4qHbHMHunOd68O7bRAt-xGPC5OOcuoqsg&oh=00_Af8NfJ3aMA4_KRR_NLMNZTK2hHOUY2cN7Or5HiGfnvxFkQ&oe=6A36D6C2", "img_type": "img", "video": null, "win_score": 3, "win_type": "전환", "win_flags": {"roas": true, "ctr": true, "cvr": false, "cpc": true, "purchases": false}}, {"key": "전환_26인치_재입고04_콜리_오딧", "base_key": "26인치_재입고04_콜리", "ad_id": "120248577076980667", "objective": "전환", "pa_type": "자컨", "landing": "오딧", "purpose": "전환", "mgr": "콜리", "media": "배너", "spend": 37837, "impressions": 1648, "clicks": 46, "purchases": 1.0, "revenue": 350000, "age_days": 4, "roas": 9.250205, "roas_pct": 925.0, "ctr": 2.79, "cvr": 2.17, "cpc": 823.0, "is_new": true, "old_roas_pct": 925.0, "roas_delta": 0.0, "prev_spend": 37837, "prev_ctr": 2.79, "prev_cvr": 2.17, "prev_cpc": 823.0, "prev_purchases": 1, "prev_revenue": 350000, "img": "https://scontent-sin11-1.xx.fbcdn.net/v/t45.1600-4/686449651_122111127357123564_3147507027285960397_n.png?stp=dst-jpg_tt6&_nc_cat=104&ccb=1-7&_nc_sid=d5bd00&_nc_ohc=PmefB2MUym0Q7kNvwF-7NM7&_nc_oc=AdpdXbNSSdak9lfLxB_x567uVvIXY30vQmmrhnOrJUg9swWIwlQ3Xv7J7CMQLyD1Ljo&_nc_zt=1&_nc_ht=scontent-sin11-1.xx&edm=AAwGEdEEAAAA&_nc_gid=sM8-hd7zmr8WaZwsQncXBA&_nc_tpa=Q5bMBQG9HxJPiOSUMpito0WP8yXp4LYLR-z3bERu855kOkiAvbwho3uTgdLHsAGmacg6UrXzbSQOtGta3Q&oh=00_Af_bmz21FpikpZZq6FzT-RoxiJBkwEph1HsDPbnnj89o6g&oe=6A36D519", "img_type": "img", "video": null, "win_score": null, "win_type": null, "win_flags": {}}, {"key": "전환_솔티커튼_리지_플랩", "base_key": "솔티커튼_리지", "ad_id": "120248695560010667", "objective": "전환", "pa_type": "자컨", "landing": "플랩", "purpose": "전환", "mgr": "리지", "media": "영상", "spend": 74700, "impressions": 3031, "clicks": 102, "purchases": 2.0, "revenue": 379000, "age_days": 3, "roas": 5.073628, "roas_pct": 507.0, "ctr": 3.37, "cvr": 1.96, "cpc": 732.0, "is_new": true, "old_roas_pct": 507.0, "roas_delta": 0.0, "prev_spend": 74700, "prev_ctr": 3.37, "prev_cvr": 1.96, "prev_cpc": 732.0, "prev_purchases": 2, "prev_revenue": 379000, "img": "https://www.facebook.com/ads/image/?d=AQJ4hTXXoZkDb6wl6rESk1KTA5IYfwLBkTx-aEKOe30cqv9aXG6_e9wIoLkpCg0Ln8g1uLZSp4xxPBuQOCOWxS2W1a5i1Exdp6rPHrvddeYfVRrdld0XMdp8cPAXkYcURctLf9avj6mEV69mT2Oi70FL", "img_type": "video", "video": "977776271612775", "win_score": null, "win_type": null, "win_flags": {}}], "d7_lose": [{"key": "전환_26인치_재입고02_콜리_오딧", "base_key": "26인치_재입고02_콜리", "ad_id": "120248577077000667", "objective": "전환", "pa_type": "자컨", "landing": "오딧", "purpose": "전환", "mgr": "콜리", "media": "영상", "spend": 109685, "impressions": 4589, "clicks": 96, "purchases": 0, "revenue": 0, "age_days": 4, "roas": 0, "roas_pct": 0, "ctr": 2.09, "cvr": 0.0, "cpc": 1143.0, "is_new": true, "old_roas_pct": null, "roas_delta": null, "prev_spend": 109685, "prev_ctr": 2.09, "prev_cvr": null, "prev_cpc": 1143.0, "prev_purchases": null, "prev_revenue": null, "img": "https://www.facebook.com/ads/image/?d=AQKBgg6nEczsQlSP13baGcAaxaRt-ywf44SHwdrn_IlpWqm5wPFVedJQJgq12seDwpCneLub9HEs9-1FKJ8zD3h3LTayZHPRTwR4Xxv_dBu9weSqtbQ2kH9NNHHO00dBg3V8yl605SJdprRpouCFGT9G", "img_type": "video", "video": "1513008140320859", "win_score": 0, "win_type": "전환", "win_flags": {"roas": false, "ctr": false, "cvr": false, "cpc": false, "purchases": false}}], "all_ads": [{"key": "전환_펄스레드_파트너스_소진_오딧", "base_key": "펄스레드_파트너스_소진", "ad_id": "120243398583140667", "objective": "전환", "pa_type": "PA", "landing": "오딧", "purpose": "전환", "mgr": "파트너스", "media": "영상", "spend": 2217301, "impressions": 88731, "clicks": 2699, "purchases": 29.0, "revenue": 11815300, "age_days": 96, "roas": 5.328686, "roas_pct": 533.0, "ctr": 3.04, "cvr": 1.07, "cpc": 822.0, "is_new": false, "old_roas_pct": 533.0, "roas_delta": 0.0, "prev_spend": 2217301, "prev_ctr": 3.04, "prev_cvr": 1.07, "prev_cpc": 822.0, "prev_purchases": 29, "prev_revenue": 11815300, "img": null, "img_type": "video", "video": "1932103937427171", "win_score": 3, "win_type": "전환", "win_flags": {"roas": false, "ctr": true, "cvr": false, "cpc": true, "purchases": true}}, {"key": "전환_파트너스_po0ong_플랩", "base_key": "파트너스_po0ong", "ad_id": "120243392317660667", "objective": "전환", "pa_type": "PA", "landing": "플랩", "purpose": "전환", "mgr": "파트너스", "media": "영상", "spend": 2200908, "impressions": 75900, "clicks": 2465, "purchases": 44.0, "revenue": 17685106, "age_days": 111, "roas": 8.035368, "roas_pct": 804.0, "ctr": 3.25, "cvr": 1.78, "cpc": 893.0, "is_new": false, "old_roas_pct": 804.0, "roas_delta": 0.0, "prev_spend": 2200908, "prev_ctr": 3.25, "prev_cvr": 1.78, "prev_cpc": 893.0, "prev_purchases": 44, "prev_revenue": 17685106, "img": null, "img_type": "video", "video": "821315101048750", "win_score": 3, "win_type": "전환", "win_flags": {"roas": false, "ctr": true, "cvr": false, "cpc": true, "purchases": true}}, {"key": "전환_오딧+플랩_파트너스_밍똥_오딧", "base_key": "오딧+플랩_파트너스_밍똥", "ad_id": "120247132341220667", "objective": "전환", "pa_type": "PA", "landing": "오딧", "purpose": "전환", "mgr": "파트너스", "media": "영상", "spend": 1597374, "impressions": 97205, "clicks": 2664, "purchases": 28.0, "revenue": 10745300, "age_days": 26, "roas": 6.726853, "roas_pct": 673.0, "ctr": 2.74, "cvr": 1.05, "cpc": 600.0, "is_new": false, "old_roas_pct": 673.0, "roas_delta": 0.0, "prev_spend": 1597374, "prev_ctr": 2.74, "prev_cvr": 1.05, "prev_cpc": 600.0, "prev_purchases": 28, "prev_revenue": 10745300, "img": null, "img_type": "video", "video": "1681610669498118", "win_score": 3, "win_type": "전환", "win_flags": {"roas": false, "ctr": true, "cvr": false, "cpc": true, "purchases": true}}, {"key": "전환_26인치_재입고01_콜리_오딧", "base_key": "26인치_재입고01_콜리", "ad_id": "120248577076990667", "objective": "전환", "pa_type": "자컨", "landing": "오딧", "purpose": "전환", "mgr": "콜리", "media": "영상", "spend": 1351940, "impressions": 71837, "clicks": 1316, "purchases": 34.0, "revenue": 13448800, "age_days": 4, "roas": 9.947779, "roas_pct": 995.0, "ctr": 1.83, "cvr": 2.58, "cpc": 1027.0, "is_new": true, "old_roas_pct": 995.0, "roas_delta": 0.0, "prev_spend": 1351940, "prev_ctr": 1.83, "prev_cvr": 2.58, "prev_cpc": 1027.0, "prev_purchases": 34, "prev_revenue": 13448800, "img": "https://www.facebook.com/ads/image/?d=AQL6K28zg5wS4JKBsHZD0vncQKAuwcSw-IFUAJj37jKoDw71rAX3-FfUNYOsbf3duH3th26KUoOc4YpiltSZqX3OXjn2cDpQMez-EKVOoOTtRYZragm6y4gOQe19mbSyPW8oZWPvjaw12EDvtP5FpeUv", "img_type": "video", "video": "1893787557939918", "win_score": 4, "win_type": "전환", "win_flags": {"roas": true, "ctr": false, "cvr": true, "cpc": true, "purchases": true}}, {"key": "전환_파트너스_고구마_플랩", "base_key": "파트너스_고구마", "ad_id": "120244424403500667", "objective": "전환", "pa_type": "PA", "landing": "플랩", "purpose": "전환", "mgr": "파트너스", "media": "영상", "spend": 692361, "impressions": 23319, "clicks": 624, "purchases": 5.0, "revenue": 2425700, "age_days": 74, "roas": 3.503519, "roas_pct": 350.0, "ctr": 2.68, "cvr": 0.8, "cpc": 1110.0, "is_new": false, "old_roas_pct": 350.0, "roas_delta": 0.0, "prev_spend": 692361, "prev_ctr": 2.68, "prev_cvr": 0.8, "prev_cpc": 1110.0, "prev_purchases": 5, "prev_revenue": 2425700, "img": null, "img_type": "video", "video": "1349825083844673", "win_score": 1, "win_type": "전환", "win_flags": {"roas": false, "ctr": true, "cvr": false, "cpc": false, "purchases": false}}, {"key": "전환_오딧재입고02_콜리_오딧", "base_key": "오딧재입고02_콜리", "ad_id": "120247693697390667", "objective": "전환", "pa_type": "자컨", "landing": "오딧", "purpose": "전환", "mgr": "콜리", "media": "배너", "spend": 651897, "impressions": 30683, "clicks": 664, "purchases": 15.0, "revenue": 5810527, "age_days": 17, "roas": 8.913259, "roas_pct": 891.0, "ctr": 2.16, "cvr": 2.26, "cpc": 982.0, "is_new": false, "old_roas_pct": 891.0, "roas_delta": 0.0, "prev_spend": 651897, "prev_ctr": 2.16, "prev_cvr": 2.26, "prev_cpc": 982.0, "prev_purchases": 15, "prev_revenue": 5810527, "img": "https://scontent-sin6-3.xx.fbcdn.net/v/t45.1600-4/676526023_122109712401123564_1460242989174341096_n.png?stp=dst-jpg_tt6&_nc_cat=110&ccb=1-7&_nc_sid=d5bd00&_nc_ohc=sDnhRzabuJsQ7kNvwGgLEOg&_nc_oc=AdqlrQzQBtp4iMlJg1YFtNXskSeRc80d7k7z_c2sSdKAIjpM7GXAfUhtCQCVbxK5DVE&_nc_zt=1&_nc_ht=scontent-sin6-3.xx&edm=AAwGEdEEAAAA&_nc_gid=5UZxNZvyZBM8SPh51RHmCg&_nc_tpa=Q5bMBQHfHQLhOhcwDg477m655oiquqij8ppS5DOqMOfMPsrSCCg8V-pBU3F5eT6skIYgRGQlQHil6JT85w&oh=00_Af96fBmdr0vrqvTUT46Xe6kGWMGkb1IRw9vK98uadNW2SQ&oe=6A36FB81", "img_type": "img", "video": null, "win_score": 3, "win_type": "전환", "win_flags": {"roas": true, "ctr": false, "cvr": false, "cpc": true, "purchases": true}}, {"key": "전환_오딧+플랩_파트너스_나나_오딧", "base_key": "오딧+플랩_파트너스_나나", "ad_id": "120247265165380667", "objective": "전환", "pa_type": "PA", "landing": "오딧", "purpose": "전환", "mgr": "파트너스", "media": "영상", "spend": 620937, "impressions": 34878, "clicks": 1070, "purchases": 16.0, "revenue": 5868900, "age_days": 24, "roas": 9.451684, "roas_pct": 945.0, "ctr": 3.07, "cvr": 1.5, "cpc": 580.0, "is_new": false, "old_roas_pct": 945.0, "roas_delta": 0.0, "prev_spend": 620937, "prev_ctr": 3.07, "prev_cvr": 1.5, "prev_cpc": 580.0, "prev_purchases": 16, "prev_revenue": 5868900, "img": null, "img_type": "video", "video": "1518469182978189", "win_score": 4, "win_type": "전환", "win_flags": {"roas": true, "ctr": true, "cvr": false, "cpc": true, "purchases": true}}, {"key": "전환_펄스레드재입고03_콜리_오딧", "base_key": "펄스레드재입고03_콜리", "ad_id": "120247747183630667", "objective": "전환", "pa_type": "자컨", "landing": "오딧", "purpose": "전환", "mgr": "콜리", "media": "배너", "spend": 604954, "impressions": 27554, "clicks": 654, "purchases": 24.0, "revenue": 10246335, "age_days": 16, "roas": 16.937379, "roas_pct": 1694.0, "ctr": 2.37, "cvr": 3.67, "cpc": 925.0, "is_new": false, "old_roas_pct": 1694.0, "roas_delta": 0.0, "prev_spend": 604954, "prev_ctr": 2.37, "prev_cvr": 3.67, "prev_cpc": 925.0, "prev_purchases": 24, "prev_revenue": 10246335, "img": "https://scontent-sin11-1.xx.fbcdn.net/v/t45.1600-4/677693950_122109805701123564_297151026179670161_n.png?stp=dst-jpg_tt6&_nc_cat=104&ccb=1-7&_nc_sid=d5bd00&_nc_ohc=QpJiHs6UUrsQ7kNvwHxQALZ&_nc_oc=Adpsvgz5T-aJMfJtdIUALY-ZOqKZcciINLPbcDOxJY_qY-P4sWTj0JM5QhAZQ-sQU44&_nc_zt=1&_nc_ht=scontent-sin11-1.xx&edm=AAwGEdEEAAAA&_nc_gid=ffPPi6QV_CD7WHtTbS8f4g&_nc_tpa=Q5bMBQF_ykso6qZPnXsETbKLCTF-BKb2IJoXv4oJgv8-7VYMAH55PEUpubgWuUuTOJvAR-yNuoHtVBkE3g&oh=00_Af9hqY4xWQas5IGT5qlfw04mF25s94SqEjAuGNx4kGUhSw&oe=6A370297", "img_type": "img", "video": null, "win_score": 5, "win_type": "전환", "win_flags": {"roas": true, "ctr": true, "cvr": true, "cpc": true, "purchases": true}}, {"key": "전환_26인치_재입고01-1_콜리_오딧", "base_key": "26인치_재입고01-1_콜리", "ad_id": "120248577077010667", "objective": "전환", "pa_type": "자컨", "landing": "오딧", "purpose": "전환", "mgr": "콜리", "media": "영상", "spend": 401993, "impressions": 15414, "clicks": 359, "purchases": 21.0, "revenue": 8526900, "age_days": 4, "roas": 21.211563, "roas_pct": 2121.0, "ctr": 2.33, "cvr": 5.85, "cpc": 1120.0, "is_new": true, "old_roas_pct": 2121.0, "roas_delta": 0.0, "prev_spend": 401993, "prev_ctr": 2.33, "prev_cvr": 5.85, "prev_cpc": 1120.0, "prev_purchases": 21, "prev_revenue": 8526900, "img": "https://www.facebook.com/ads/image/?d=AQIUzJmjpkaUEeAyYn01KF01yfK0sz9QHBgUBh71R3XnuRXVf1imdcrEJY0-kcc7a3TtYbR7M60_8YDbDTPMNExUOreu5MaRPbVaKdiiJQUe-eEd3b_WrSylNtDHK3QuSG2F-rJsbvmippZHK_FLx4kE", "img_type": "video", "video": "1522790255928346", "win_score": 4, "win_type": "전환", "win_flags": {"roas": true, "ctr": true, "cvr": true, "cpc": false, "purchases": true}}, {"key": "전환_펄스레드_수하물_콜리_오딧", "base_key": "펄스레드_수하물_콜리", "ad_id": "120244125517820667", "objective": "전환", "pa_type": "자컨", "landing": "오딧", "purpose": "전환", "mgr": "콜리", "media": "영상", "spend": 392599, "impressions": 14148, "clicks": 341, "purchases": 9.0, "revenue": 3406250, "age_days": 79, "roas": 8.676156, "roas_pct": 868.0, "ctr": 2.41, "cvr": 2.64, "cpc": 1151.0, "is_new": false, "old_roas_pct": 868.0, "roas_delta": 0.0, "prev_spend": 392599, "prev_ctr": 2.41, "prev_cvr": 2.64, "prev_cpc": 1151.0, "prev_purchases": 9, "prev_revenue": 3406250, "img": "https://www.facebook.com/ads/image/?d=AQJsuJYytf8EPTNjinTL_xPXo2y-bSPmQsuypV5pM-_--x4iyUUOgKf4MW8KKoailwMemo4hwQOkvjjtkAM4627qm9P2c246NWlG7GtYhh54zOumzW8kNzfKpbql-x_n2KP90ryV-beqz0zpQbBlcC-B", "img_type": "video", "video": "989354130218060", "win_score": 2, "win_type": "전환", "win_flags": {"roas": false, "ctr": true, "cvr": true, "cpc": false, "purchases": false}}, {"key": "전환_솔티브랜드02_리지_플랩", "base_key": "솔티브랜드02_리지", "ad_id": "120248695560000667", "objective": "전환", "pa_type": "자컨", "landing": "플랩", "purpose": "전환", "mgr": "리지", "media": "배너", "spend": 343758, "impressions": 12072, "clicks": 422, "purchases": 8.0, "revenue": 3327200, "age_days": 3, "roas": 9.678902, "roas_pct": 968.0, "ctr": 3.5, "cvr": 1.9, "cpc": 815.0, "is_new": true, "old_roas_pct": 968.0, "roas_delta": 0.0, "prev_spend": 343758, "prev_ctr": 3.5, "prev_cvr": 1.9, "prev_cpc": 815.0, "prev_purchases": 8, "prev_revenue": 3327200, "img": "https://scontent-sin11-1.xx.fbcdn.net/v/t45.1600-4/691806695_122101476549297071_6523363003118697610_n.png?stp=dst-jpg_tt6&_nc_cat=105&ccb=1-7&_nc_sid=d5bd00&_nc_ohc=rdcIUtgpCrUQ7kNvwEbE2z4&_nc_oc=AdqwG0qgltQeCTrwG4KkXcsz45DKdwsENXQnKboSwZPk2zbPnP3as3IO-YbvJNUL1l8&_nc_zt=1&_nc_ht=scontent-sin11-1.xx&edm=AAwGEdEEAAAA&_nc_gid=2AfidITGas9_-uch8QcHgA&_nc_tpa=Q5bMBQHlsg9LTFeFFOZ5Mdqj1YvjH3by-G1GRr3ablWIIX4Ux4qHbHMHunOd68O7bRAt-xGPC5OOcuoqsg&oh=00_Af8NfJ3aMA4_KRR_NLMNZTK2hHOUY2cN7Or5HiGfnvxFkQ&oe=6A36D6C2", "img_type": "img", "video": null, "win_score": 3, "win_type": "전환", "win_flags": {"roas": true, "ctr": true, "cvr": false, "cpc": true, "purchases": false}}, {"key": "전환_펄스레드_컬러01_세레나_오딧", "base_key": "펄스레드_컬러01_세레나", "ad_id": "120244507767160667", "objective": "전환", "pa_type": "자컨", "landing": "오딧", "purpose": "전환", "mgr": "세레나", "media": "영상", "spend": 342146, "impressions": 14796, "clicks": 411, "purchases": 8.0, "revenue": 4246000, "age_days": 72, "roas": 12.409907, "roas_pct": 1241.0, "ctr": 2.78, "cvr": 1.95, "cpc": 832.0, "is_new": false, "old_roas_pct": 1241.0, "roas_delta": 0.0, "prev_spend": 342146, "prev_ctr": 2.78, "prev_cvr": 1.95, "prev_cpc": 832.0, "prev_purchases": 8, "prev_revenue": 4246000, "img": "https://www.facebook.com/ads/image/?d=AQICdo05fLB-OvhqicYXFzenGxnDaHn_EiTzL5sd2gynwzwggaiXz9yfnVTlkrvaQnRn7qajwzdVU7BCP0wvbJvPxeRzPw2U40sXFtzZIiFbrWh1xlUBcrvVVByqCcjUNmUVaMF0-xbSDb5CELEsmLkq", "img_type": "video", "video": "1240583091622496", "win_score": 3, "win_type": "전환", "win_flags": {"roas": true, "ctr": true, "cvr": false, "cpc": true, "purchases": false}}, {"key": "전환_솔티화이트_콜리_오딧", "base_key": "솔티화이트_콜리", "ad_id": "120245325294920667", "objective": "전환", "pa_type": "자컨", "landing": "오딧", "purpose": "전환", "mgr": "콜리", "media": "영상", "spend": 332211, "impressions": 16463, "clicks": 284, "purchases": 4.0, "revenue": 1363500, "age_days": 58, "roas": 4.104319, "roas_pct": 410.0, "ctr": 1.73, "cvr": 1.41, "cpc": 1170.0, "is_new": false, "old_roas_pct": 410.0, "roas_delta": 0.0, "prev_spend": 332211, "prev_ctr": 1.73, "prev_cvr": 1.41, "prev_cpc": 1170.0, "prev_purchases": 4, "prev_revenue": 1363500, "img": "https://www.facebook.com/ads/image/?d=AQKAPgY4JaHeGuoylwFsMLkxNxbjHd4XCNVayt58eUrO85GCD-y7io4mS4cdT9N3CtvuxTUzR3dOyM4yKbwj1serJ-Cc_XWLWxXL2GIPVv5NAiFJouPY89_Yw2TUozl7fEYZZNonZySRyC92xSiJMsth", "img_type": "video", "video": "1230682982555529", "win_score": 0, "win_type": "전환", "win_flags": {"roas": false, "ctr": false, "cvr": false, "cpc": false, "purchases": false}}, {"key": "전환_오딧+플랩_29플랩롱폼_세레나_오딧", "base_key": "오딧+플랩_29플랩롱폼_세레나", "ad_id": "120247312312140667", "objective": "전환", "pa_type": "자컨", "landing": "오딧", "purpose": "전환", "mgr": "세레나", "media": "영상", "spend": 292505, "impressions": 15766, "clicks": 403, "purchases": 2.0, "revenue": 640000, "age_days": 23, "roas": 2.187997, "roas_pct": 219.0, "ctr": 2.56, "cvr": 0.5, "cpc": 726.0, "is_new": false, "old_roas_pct": 219.0, "roas_delta": 0.0, "prev_spend": 292505, "prev_ctr": 2.56, "prev_cvr": 0.5, "prev_cpc": 726.0, "prev_purchases": 2, "prev_revenue": 640000, "img": null, "img_type": "img", "video": null, "win_score": 2, "win_type": "전환", "win_flags": {"roas": false, "ctr": true, "cvr": false, "cpc": true, "purchases": false}}, {"key": "전환_오딧+플랩_파트너스_신혼쀼_오딧", "base_key": "오딧+플랩_파트너스_신혼쀼", "ad_id": "120247193904430667", "objective": "전환", "pa_type": "PA", "landing": "오딧", "purpose": "전환", "mgr": "파트너스", "media": "영상", "spend": 280822, "impressions": 28545, "clicks": 262, "purchases": 7.0, "revenue": 2530500, "age_days": 25, "roas": 9.011046, "roas_pct": 901.0, "ctr": 0.92, "cvr": 2.67, "cpc": 1072.0, "is_new": false, "old_roas_pct": 901.0, "roas_delta": 0.0, "prev_spend": 280822, "prev_ctr": 0.92, "prev_cvr": 2.67, "prev_cpc": 1072.0, "prev_purchases": 7, "prev_revenue": 2530500, "img": null, "img_type": "video", "video": "1875981276444344", "win_score": 3, "win_type": "전환", "win_flags": {"roas": true, "ctr": false, "cvr": true, "cpc": true, "purchases": false}}, {"key": "전환_솔티블루_상시1_리지_오딧", "base_key": "솔티블루_상시1_리지", "ad_id": "120242747398920667", "objective": "전환", "pa_type": "자컨", "landing": "오딧", "purpose": "전환", "mgr": "리지", "media": "배너", "spend": 271201, "impressions": 17705, "clicks": 233, "purchases": 9.0, "revenue": 3265000, "age_days": 111, "roas": 12.039041, "roas_pct": 1204.0, "ctr": 1.32, "cvr": 3.86, "cpc": 1164.0, "is_new": false, "old_roas_pct": 1204.0, "roas_delta": 0.0, "prev_spend": 271201, "prev_ctr": 1.32, "prev_cvr": 3.86, "prev_cpc": 1164.0, "prev_purchases": 9, "prev_revenue": 3265000, "img": null, "img_type": "img", "video": null, "win_score": 2, "win_type": "전환", "win_flags": {"roas": true, "ctr": false, "cvr": true, "cpc": false, "purchases": false}}, {"key": "전환_바퀴02_세레나_오딧", "base_key": "바퀴02_세레나", "ad_id": "120242867530010667", "objective": "전환", "pa_type": "자컨", "landing": "오딧", "purpose": "전환", "mgr": "세레나", "media": "영상", "spend": 240189, "impressions": 10421, "clicks": 175, "purchases": 5.0, "revenue": 2044000, "age_days": 108, "roas": 8.509965, "roas_pct": 851.0, "ctr": 1.68, "cvr": 2.86, "cpc": 1373.0, "is_new": false, "old_roas_pct": 851.0, "roas_delta": 0.0, "prev_spend": 240189, "prev_ctr": 1.68, "prev_cvr": 2.86, "prev_cpc": 1373.0, "prev_purchases": 5, "prev_revenue": 2044000, "img": "https://www.facebook.com/ads/image/?d=AQIIgJ_GTZjyGrUKLoZ5NHcUNwNtAjJtUmT2qs7amaxw0U5ycMbVKWhyjCMQ7-WKjsAv7AG1SPuREdlCvWyQCDoTWJVxdFy81jdjrbs6HnNca7OJ1_CTfG6WutNH01yxbtGTssaL9BbVMAfBLddzo2BX", "img_type": "video", "video": "1327773319415807", "win_score": 1, "win_type": "전환", "win_flags": {"roas": false, "ctr": false, "cvr": true, "cpc": false, "purchases": false}}, {"key": "전환_파트너스_이서현_오딧", "base_key": "파트너스_이서현", "ad_id": "120246954997990667", "objective": "전환", "pa_type": "PA", "landing": "오딧", "purpose": "전환", "mgr": "파트너스", "media": "영상", "spend": 233423, "impressions": 14683, "clicks": 343, "purchases": 1.0, "revenue": 370000, "age_days": 30, "roas": 1.585105, "roas_pct": 159.0, "ctr": 2.34, "cvr": 0.29, "cpc": 681.0, "is_new": false, "old_roas_pct": 159.0, "roas_delta": 0.0, "prev_spend": 233423, "prev_ctr": 2.34, "prev_cvr": 0.29, "prev_cpc": 681.0, "prev_purchases": 1, "prev_revenue": 370000, "img": null, "img_type": "video", "video": "4338021316516808", "win_score": 2, "win_type": "전환", "win_flags": {"roas": false, "ctr": true, "cvr": false, "cpc": true, "purchases": false}}, {"key": "전환_솔티블루_리뷰04_세레나_오딧", "base_key": "솔티블루_리뷰04_세레나", "ad_id": "120242867735480667", "objective": "전환", "pa_type": "자컨", "landing": "오딧", "purpose": "전환", "mgr": "세레나", "media": "배너", "spend": 221302, "impressions": 8757, "clicks": 108, "purchases": 2.0, "revenue": 720000, "age_days": 108, "roas": 3.253473, "roas_pct": 325.0, "ctr": 1.23, "cvr": 1.85, "cpc": 2049.0, "is_new": false, "old_roas_pct": 325.0, "roas_delta": 0.0, "prev_spend": 221302, "prev_ctr": 1.23, "prev_cvr": 1.85, "prev_cpc": 2049.0, "prev_purchases": 2, "prev_revenue": 720000, "img": "https://scontent-sin11-2.xx.fbcdn.net/v/t45.1600-4/621136940_2315598045619250_2607685837400810331_n.png?stp=dst-jpg_tt6&_nc_cat=108&ccb=1-7&_nc_sid=d5bd00&_nc_ohc=QegHC-fyNrgQ7kNvwHey9Hh&_nc_oc=AdrVthUNL6wap9spCLRr4ZiTX5fzXlbqIIDas_J18KW1JlMZYrxfnrqIyl5uP_UBqrU&_nc_zt=1&_nc_ht=scontent-sin11-2.xx&edm=AAwGEdEEAAAA&_nc_gid=WRMhZYu9qmir1MkL2whXgA&_nc_tpa=Q5bMBQGE8e9n5kAEWkbYMggrc-EYeUqxsmUPKE8K4W6DVWhD5kcv_0Egfy78qcqG16g2_TBWmJ0Rn95WWQ&oh=00_Af-7zZIr8NjhwKCjPQxMkh_-nPmHYtuqJjAeOPRFFYN52A&oe=6A36EC46", "img_type": "img", "video": null, "win_score": 0, "win_type": "전환", "win_flags": {"roas": false, "ctr": false, "cvr": false, "cpc": false, "purchases": false}}, {"key": "전환_솔티블루01_콜리_오딧", "base_key": "솔티블루01_콜리", "ad_id": "120248226454160667", "objective": "전환", "pa_type": "자컨", "landing": "오딧", "purpose": "전환", "mgr": "콜리", "media": "배너", "spend": 208765, "impressions": 6733, "clicks": 181, "purchases": 8.0, "revenue": 2524000, "age_days": 10, "roas": 12.090149, "roas_pct": 1209.0, "ctr": 2.69, "cvr": 4.42, "cpc": 1153.0, "is_new": false, "old_roas_pct": 1209.0, "roas_delta": 0.0, "prev_spend": 208765, "prev_ctr": 2.69, "prev_cvr": 4.42, "prev_cpc": 1153.0, "prev_purchases": 8, "prev_revenue": 2524000, "img": "https://scontent-sin2-2.xx.fbcdn.net/v/t45.1600-4/676693174_122110490781123564_7475291067194090057_n.png?stp=dst-jpg_tt6&_nc_cat=103&ccb=1-7&_nc_sid=d5bd00&_nc_ohc=sbBCKwA9HDYQ7kNvwFHOb_q&_nc_oc=AdpncR3drDPESt4DOKdYv5KdWlu_jejrIlkihmHi84wnFAi_rmwRC_AvVcjpUXAlw8A&_nc_zt=1&_nc_ht=scontent-sin2-2.xx&edm=AAwGEdEEAAAA&_nc_gid=rem8Pmef1omZxPCgCmlMzA&_nc_tpa=Q5bMBQEDHGwmNl-AEsTTWI7xvPXrTNrFRgueudQZ_ROwBwsKUx0tfqnCTqUR-c24bM5rTtMy9FINUUofzw&oh=00_Af8_-fByxC2U4rD774ZStfrS1jqpGl218byzFich8WtYfQ&oe=6A36CF8C", "img_type": "img", "video": null, "win_score": 3, "win_type": "전환", "win_flags": {"roas": true, "ctr": true, "cvr": true, "cpc": false, "purchases": false}}, {"key": "전환_펄스레드_브랜디드_콜리_오딧", "base_key": "펄스레드_브랜디드_콜리", "ad_id": "120244870415860667", "objective": "전환", "pa_type": "자컨", "landing": "오딧", "purpose": "전환", "mgr": "콜리", "media": "영상", "spend": 201919, "impressions": 6688, "clicks": 136, "purchases": 5.0, "revenue": 1289889, "age_days": 65, "roas": 6.388151, "roas_pct": 639.0, "ctr": 2.03, "cvr": 3.68, "cpc": 1485.0, "is_new": false, "old_roas_pct": 639.0, "roas_delta": 0.0, "prev_spend": 201919, "prev_ctr": 2.03, "prev_cvr": 3.68, "prev_cpc": 1485.0, "prev_purchases": 5, "prev_revenue": 1289889, "img": "https://www.facebook.com/ads/image/?d=AQLiyguLcuvgV5V7OiihEocCvTefqqPuKnj35TyvRnKU-bM9G9kl2cmrlVKMWYqHyz1LPxMgxBnXUWV299WbAfvruyoQj8gCf2hNVTCwDXjLJx20H3jhmS0V96cg9ZsYSNJTLQyDFPU0CvlLFVvnbvEf", "img_type": "video", "video": "1249819554002172", "win_score": 1, "win_type": "전환", "win_flags": {"roas": false, "ctr": false, "cvr": true, "cpc": false, "purchases": false}}, {"key": "전환_26인치_세레나_오딧", "base_key": "26인치_세레나", "ad_id": "120243846307880667", "objective": "전환", "pa_type": "자컨", "landing": "오딧", "purpose": "전환", "mgr": "세레나", "media": "영상", "spend": 199647, "impressions": 6879, "clicks": 113, "purchases": 5.0, "revenue": 2292300, "age_days": 86, "roas": 11.481765, "roas_pct": 1148.0, "ctr": 1.64, "cvr": 4.42, "cpc": 1767.0, "is_new": false, "old_roas_pct": 1148.0, "roas_delta": 0.0, "prev_spend": 199647, "prev_ctr": 1.64, "prev_cvr": 4.42, "prev_cpc": 1767.0, "prev_purchases": 5, "prev_revenue": 2292300, "img": "https://www.facebook.com/ads/image/?d=AQJ_-fDImhzpixfzp1Gg1HMsHW_PVZQzMdf_YjFPh4el-2cntzaKF6pOpdLUi-qCKRFS-1VZRgEASa_geq-kF504jcbkScQmHUYC4pHPPr64_dmlVEKJWo145T_68ax_PKpIrTTMaJSHHHkw1_5PYt5-", "img_type": "video", "video": "945014054763882", "win_score": 2, "win_type": "전환", "win_flags": {"roas": true, "ctr": false, "cvr": true, "cpc": false, "purchases": false}}, {"key": "전환_26인치_재입고03_콜리_오딧", "base_key": "26인치_재입고03_콜리", "ad_id": "120248577076970667", "objective": "전환", "pa_type": "자컨", "landing": "오딧", "purpose": "전환", "mgr": "콜리", "media": "배너", "spend": 199423, "impressions": 7755, "clicks": 152, "purchases": 10.0, "revenue": 3196000, "age_days": 4, "roas": 16.026236, "roas_pct": 1603.0, "ctr": 1.96, "cvr": 6.58, "cpc": 1312.0, "is_new": true, "old_roas_pct": 1603.0, "roas_delta": 0.0, "prev_spend": 199423, "prev_ctr": 1.96, "prev_cvr": 6.58, "prev_cpc": 1312.0, "prev_purchases": 10, "prev_revenue": 3196000, "img": "https://scontent-sin11-1.xx.fbcdn.net/v/t45.1600-4/686041817_122111127267123564_487314875706961986_n.png?stp=dst-jpg_tt6&_nc_cat=104&ccb=1-7&_nc_sid=d5bd00&_nc_ohc=KGdC8NRHjgAQ7kNvwFSQg2e&_nc_oc=AdoVqzU6zkNJlXQW3fn0qVP7ODLGL4zPCNr_MXSN2r8802ufoZPevdje9584qB5WSzg&_nc_zt=1&_nc_ht=scontent-sin11-1.xx&edm=AAwGEdEEAAAA&_nc_gid=Zu2brkAvDGsELzhzzbdGxQ&_nc_tpa=Q5bMBQG7RY9Nc5xPNodonbgripxp--AkY-b5sc44wb09cJarK7XUdbOAlQ5yQba0nvZBnaYmC6ES1aHprQ&oh=00_Af-o3GsJ9J4IlIgY6pxi9smohqUngmix5aETQdFI1tBHAQ&oe=6A36FF47", "img_type": "img", "video": null, "win_score": 2, "win_type": "전환", "win_flags": {"roas": true, "ctr": false, "cvr": true, "cpc": false, "purchases": false}}, {"key": "전환_펄스레드재입고01_콜리_오딧", "base_key": "펄스레드재입고01_콜리", "ad_id": "120247693697380667", "objective": "전환", "pa_type": "자컨", "landing": "오딧", "purpose": "전환", "mgr": "콜리", "media": "배너", "spend": 196695, "impressions": 9586, "clicks": 181, "purchases": 4.0, "revenue": 1050900, "age_days": 17, "roas": 5.34279, "roas_pct": 534.0, "ctr": 1.89, "cvr": 2.21, "cpc": 1087.0, "is_new": false, "old_roas_pct": 534.0, "roas_delta": 0.0, "prev_spend": 196695, "prev_ctr": 1.89, "prev_cvr": 2.21, "prev_cpc": 1087.0, "prev_purchases": 4, "prev_revenue": 1050900, "img": "https://scontent-sin2-2.xx.fbcdn.net/v/t45.1600-4/678309205_122109712449123564_5960323955078666137_n.png?stp=dst-jpg_tt6&_nc_cat=103&ccb=1-7&_nc_sid=d5bd00&_nc_ohc=LR1E4AqGQMkQ7kNvwEzVx-w&_nc_oc=AdpVpnopo7M0fHe76fwk4kDMd65s-kKWb09uzRE3RTtuujJgzINQYj3dHuen_m0ebaw&_nc_zt=1&_nc_ht=scontent-sin2-2.xx&edm=AAwGEdEEAAAA&_nc_gid=A3UzY_F6hnzh9nLNJ80suA&_nc_tpa=Q5bMBQEAxYk8LSA64Eli0bVdCduebbqCJ_TAoQ_5wA6U4DRTGsCe0Tp5822ph-xfWIkqfAaDi38W9R9M2Q&oh=00_Af-fOyHkC-yQJs_YGW6uXGdeBL1XGXLPr9lqzjI3YA87yQ&oe=6A36F743", "img_type": "img", "video": null, "win_score": 1, "win_type": "전환", "win_flags": {"roas": false, "ctr": false, "cvr": false, "cpc": true, "purchases": false}}, {"key": "전환_26인치02_리지_오딧", "base_key": "26인치02_리지", "ad_id": "120243237878070667", "objective": "전환", "pa_type": "자컨", "landing": "오딧", "purpose": "전환", "mgr": "리지", "media": "영상", "spend": 160775, "impressions": 5026, "clicks": 168, "purchases": 5.0, "revenue": 2083500, "age_days": 100, "roas": 12.959104, "roas_pct": 1296.0, "ctr": 3.34, "cvr": 2.98, "cpc": 957.0, "is_new": false, "old_roas_pct": 1296.0, "roas_delta": 0.0, "prev_spend": 160775, "prev_ctr": 3.34, "prev_cvr": 2.98, "prev_cpc": 957.0, "prev_purchases": 5, "prev_revenue": 2083500, "img": "https://www.facebook.com/ads/image/?d=AQIUfvcWjbOJJ8HI43sDDflQ1if2QzLs0E8O19ivlkbxEX7EO4YtA6sHFGEikbxG1fxk_KKXKfbN8OKkZamb0bzKtXnFF4mis4wWtCHKfkLrotaHdZnOi0mJo405jADGww3fj5e114anUBhRVY6tvCuf", "img_type": "video", "video": "1233221324808978", "win_score": 4, "win_type": "전환", "win_flags": {"roas": true, "ctr": true, "cvr": true, "cpc": true, "purchases": false}}, {"key": "전환_공항면세02_세레나_플랩", "base_key": "공항면세02_세레나", "ad_id": "120246876349260667", "objective": "전환", "pa_type": "자컨", "landing": "플랩", "purpose": "전환", "mgr": "세레나", "media": "영상", "spend": 148530, "impressions": 4596, "clicks": 85, "purchases": 2.0, "revenue": 950000, "age_days": 31, "roas": 6.396014, "roas_pct": 640.0, "ctr": 1.85, "cvr": 2.35, "cpc": 1747.0, "is_new": false, "old_roas_pct": 640.0, "roas_delta": 0.0, "prev_spend": 148530, "prev_ctr": 1.85, "prev_cvr": 2.35, "prev_cpc": 1747.0, "prev_purchases": 2, "prev_revenue": 950000, "img": "https://scontent-sin2-3.xx.fbcdn.net/v/t45.1600-4/669237804_122117313591225536_2260723910541121449_n.png?stp=dst-jpg_tt6&_nc_cat=107&ccb=1-7&_nc_sid=d5bd00&_nc_ohc=cLrVI9M8s4cQ7kNvwFCJdig&_nc_oc=AdoWfypUDTODaVISwzJBr1r3nV2A-O1I8VEGN8I2BAi1AGHg3mPvG5zr4DKEaItOszQ&_nc_zt=1&_nc_ht=scontent-sin2-3.xx&edm=AAwGEdEEAAAA&_nc_gid=ycnNNO2x_i-Xn8jJWNdr4A&_nc_tpa=Q5bMBQGkIFEzm0A_YM2ADwx8tqb2ABC46KvnJ_1uT9GVNvc3awuh-SrpdlaeJl3scUgSHRl1AXHfZ6vWzA&oh=00_Af8QI0IG7PbNivlJ8W9II_Gy79D3KIIIAkQZ9WBZt0A5RQ&oe=6A36E6A8", "img_type": "img", "video": null, "win_score": 0, "win_type": "전환", "win_flags": {"roas": false, "ctr": false, "cvr": false, "cpc": false, "purchases": false}}, {"key": "전환_펄스레드01_콜리_오딧", "base_key": "펄스레드01_콜리", "ad_id": "120248226454150667", "objective": "전환", "pa_type": "자컨", "landing": "오딧", "purpose": "전환", "mgr": "콜리", "media": "영상", "spend": 146673, "impressions": 6913, "clicks": 132, "purchases": 6.0, "revenue": 1556045, "age_days": 10, "roas": 10.60894, "roas_pct": 1061.0, "ctr": 1.91, "cvr": 4.55, "cpc": 1111.0, "is_new": false, "old_roas_pct": 1061.0, "roas_delta": 0.0, "prev_spend": 146673, "prev_ctr": 1.91, "prev_cvr": 4.55, "prev_cpc": 1111.0, "prev_purchases": 6, "prev_revenue": 1556045, "img": "https://www.facebook.com/ads/image/?d=AQJMZlNnuvMnFoAc7wiMKx-aViFAqxH6hbU5NTrJgDErVdWXiqhmDuarK5HvCJ499Blb9LnDPe6F7DqkqB_lOkGKZCKtQyOXPTcEiDcbicZZep-WXs5gBSIb-frQCjnGMXGafdjzWHrV7lntPOOhl6ci", "img_type": "video", "video": "1679594143049574", "win_score": 2, "win_type": "전환", "win_flags": {"roas": true, "ctr": false, "cvr": true, "cpc": false, "purchases": false}}, {"key": "전환_오딧+플랩_파트너스_란_오딧", "base_key": "오딧+플랩_파트너스_란", "ad_id": "120246460199100667", "objective": "전환", "pa_type": "PA", "landing": "오딧", "purpose": "전환", "mgr": "파트너스", "media": "영상", "spend": 134146, "impressions": 7299, "clicks": 151, "purchases": 2.0, "revenue": 720000, "age_days": 39, "roas": 5.367286, "roas_pct": 537.0, "ctr": 2.07, "cvr": 1.32, "cpc": 888.0, "is_new": false, "old_roas_pct": 537.0, "roas_delta": 0.0, "prev_spend": 134146, "prev_ctr": 2.07, "prev_cvr": 1.32, "prev_cpc": 888.0, "prev_purchases": 2, "prev_revenue": 720000, "img": null, "img_type": "video", "video": "2821170848244375", "win_score": 1, "win_type": "전환", "win_flags": {"roas": false, "ctr": false, "cvr": false, "cpc": true, "purchases": false}}, {"key": "전환_플랩리뷰04_콜리_플랩", "base_key": "플랩리뷰04_콜리", "ad_id": "120247091199820667", "objective": "전환", "pa_type": "자컨", "landing": "플랩", "purpose": "전환", "mgr": "콜리", "media": "배너", "spend": 132876, "impressions": 5814, "clicks": 136, "purchases": 4.0, "revenue": 1636000, "age_days": 31, "roas": 12.312231, "roas_pct": 1231.0, "ctr": 2.34, "cvr": 2.94, "cpc": 977.0, "is_new": false, "old_roas_pct": 1231.0, "roas_delta": 0.0, "prev_spend": 132876, "prev_ctr": 2.34, "prev_cvr": 2.94, "prev_cpc": 977.0, "prev_purchases": 4, "prev_revenue": 1636000, "img": "https://scontent-sin6-3.xx.fbcdn.net/v/t45.1600-4/665026330_122106567357123564_6695850186699127204_n.png?stp=dst-jpg_tt6&_nc_cat=110&ccb=1-7&_nc_sid=d5bd00&_nc_ohc=7CAQHzao654Q7kNvwG2G9cI&_nc_oc=AdoKGFeOALO6hVdd1KiFkVQ6NYXku2X-4C_UHKYu2CYSd13OHdAiTmnfAhxne8M_-YU&_nc_zt=1&_nc_ht=scontent-sin6-3.xx&edm=AAwGEdEEAAAA&_nc_gid=Up-jdtatbhudr95lkFwozg&_nc_tpa=Q5bMBQHWBCS8FKi0xcrb6tyZ7QiHWxRdECNQ1VwRjpmni-Iww9XsRMMn3oyEG_TLcFTTKMZ1Ekud1kZ7SA&oh=00_Af-PF7E-kP5fh430cVefAn2i6Ljum2DTkWyUmSYT1-XskA&oe=6A36D214", "img_type": "img", "video": null, "win_score": 4, "win_type": "전환", "win_flags": {"roas": true, "ctr": true, "cvr": true, "cpc": true, "purchases": false}}, {"key": "전환_26인치_재입고02_콜리_오딧", "base_key": "26인치_재입고02_콜리", "ad_id": "120248577077000667", "objective": "전환", "pa_type": "자컨", "landing": "오딧", "purpose": "전환", "mgr": "콜리", "media": "영상", "spend": 109685, "impressions": 4589, "clicks": 96, "purchases": 0, "revenue": 0, "age_days": 4, "roas": 0, "roas_pct": 0, "ctr": 2.09, "cvr": 0.0, "cpc": 1143.0, "is_new": true, "old_roas_pct": null, "roas_delta": null, "prev_spend": 109685, "prev_ctr": 2.09, "prev_cvr": null, "prev_cpc": 1143.0, "prev_purchases": null, "prev_revenue": null, "img": "https://www.facebook.com/ads/image/?d=AQKBgg6nEczsQlSP13baGcAaxaRt-ywf44SHwdrn_IlpWqm5wPFVedJQJgq12seDwpCneLub9HEs9-1FKJ8zD3h3LTayZHPRTwR4Xxv_dBu9weSqtbQ2kH9NNHHO00dBg3V8yl605SJdprRpouCFGT9G", "img_type": "video", "video": "1513008140320859", "win_score": 0, "win_type": "전환", "win_flags": {"roas": false, "ctr": false, "cvr": false, "cpc": false, "purchases": false}}, {"key": "전환_상시01_리지_플랩", "base_key": "상시01_리지", "ad_id": "120242650825630667", "objective": "전환", "pa_type": "자컨", "landing": "플랩", "purpose": "전환", "mgr": "리지", "media": "배너", "spend": 93260, "impressions": 3043, "clicks": 116, "purchases": 3.0, "revenue": 1310000, "age_days": 111, "roas": 14.046751, "roas_pct": 1405.0, "ctr": 3.81, "cvr": 2.59, "cpc": 804.0, "is_new": false, "old_roas_pct": 1405.0, "roas_delta": 0.0, "prev_spend": 93260, "prev_ctr": 3.81, "prev_cvr": 2.59, "prev_cpc": 804.0, "prev_purchases": 3, "prev_revenue": 1310000, "img": "https://scontent-sin2-1.xx.fbcdn.net/v/t45.1600-4/615822445_2310612046117850_6266214885205223036_n.png?stp=dst-jpg_tt6&_nc_cat=102&ccb=1-7&_nc_sid=d5bd00&_nc_ohc=HP91TTBFueYQ7kNvwHx0Bor&_nc_oc=AdqI2KrWizBKvs7JGO9TNf0O3IblBq6SwCJer9LUjCvsA1pJhxu2-Y-mGajubjRpwJ0&_nc_zt=1&_nc_ht=scontent-sin2-1.xx&edm=AAwGEdEEAAAA&_nc_gid=t34PvAbFu0E5s97MEtrSZw&_nc_tpa=Q5bMBQEkI-uORyOOl1EtO79XiVySYuVf-g9pgODA59c8UA2bpDsjVPBMOMhKmP5v4tdDCbr8f1JEzqo97g&oh=00_Af81P-nKoa1TjhjSER5fbsXJM3bF9KZuPhMZWGFrUMgoiA&oe=6A36F0AF", "img_type": "img", "video": null, "win_score": null, "win_type": null, "win_flags": {}}, {"key": "전환_5월연휴09_세레나_오딧", "base_key": "5월연휴09_세레나", "ad_id": "120248001875550667", "objective": "전환", "pa_type": "자컨", "landing": "오딧", "purpose": "전환", "mgr": "세레나", "media": "영상", "spend": 90543, "impressions": 4800, "clicks": 98, "purchases": 6.0, "revenue": 2644500, "age_days": 13, "roas": 29.207117, "roas_pct": 2921.0, "ctr": 2.04, "cvr": 6.12, "cpc": 924.0, "is_new": false, "old_roas_pct": 2921.0, "roas_delta": 0.0, "prev_spend": 90543, "prev_ctr": 2.04, "prev_cvr": 6.12, "prev_cpc": 924.0, "prev_purchases": 6, "prev_revenue": 2644500, "img": "https://www.facebook.com/ads/image/?d=AQLGy-HmhPISnk2mD5JeapBiRtIz-DpC09vR1fajcCKjHaw4kutF53VXemLYRksOuN55dbz9xe-1vkrPTJ_Bz9ZT7RyBmFMoLI_Is8V95lqH2JePEj_fprEWZxcQwEpPhAzawBjVrcQQihJqHi68wsRZ", "img_type": "video", "video": "1010186301342161", "win_score": null, "win_type": null, "win_flags": {}}, {"key": "전환_작누댁2차활용_07-1_세레나_오딧", "base_key": "작누댁2차활용_07-1_세레나", "ad_id": "120248582841460667", "objective": "전환", "pa_type": "자컨", "landing": "오딧", "purpose": "전환", "mgr": "세레나", "media": "영상", "spend": 79824, "impressions": 2462, "clicks": 61, "purchases": 3.0, "revenue": 1355000, "age_days": 4, "roas": 16.974845, "roas_pct": 1697.0, "ctr": 2.48, "cvr": 4.92, "cpc": 1309.0, "is_new": true, "old_roas_pct": 1697.0, "roas_delta": 0.0, "prev_spend": 79824, "prev_ctr": 2.48, "prev_cvr": 4.92, "prev_cpc": 1309.0, "prev_purchases": 3, "prev_revenue": 1355000, "img": "https://www.facebook.com/ads/image/?d=AQJjJ84RolD5d91Q8n7JnIAiynzLmIsRqv1WKaDDZHE4TIHZL3KbIkt6nO-awKlUtuObqw4hXQQAFoTuE8_kRosogdVkCSBiR5Y0zlQs9sRtNHp05JmE60mbIvFZa6sVFfmzT7Am_pSvuDUJkwz1sHXj", "img_type": "video", "video": "2306821976517932", "win_score": null, "win_type": null, "win_flags": {}}, {"key": "전환_바퀴01_세레나_오딧", "base_key": "바퀴01_세레나", "ad_id": "120242867530000667", "objective": "전환", "pa_type": "자컨", "landing": "오딧", "purpose": "전환", "mgr": "세레나", "media": "영상", "spend": 77448, "impressions": 3413, "clicks": 52, "purchases": 1.0, "revenue": 685700, "age_days": 108, "roas": 8.853682, "roas_pct": 885.0, "ctr": 1.52, "cvr": 1.92, "cpc": 1489.0, "is_new": false, "old_roas_pct": 885.0, "roas_delta": 0.0, "prev_spend": 77448, "prev_ctr": 1.52, "prev_cvr": 1.92, "prev_cpc": 1489.0, "prev_purchases": 1, "prev_revenue": 685700, "img": "https://www.facebook.com/ads/image/?d=AQJEU-RTnWc3_w6YBuEVb7d99BIaqLNfxbu8V2C2XTlWcwiOqjLtPJK_DwUXKcjn8Wcd2Anl946V_ttQpfDEmpoSc2ySLiKKYsGwlGtFxgWmQp6ZYCD646fRHed09a6KHN66535VAaphN-k05hN4h84J", "img_type": "video", "video": "875187775268732", "win_score": null, "win_type": null, "win_flags": {}}, {"key": "전환_솔티커튼_리지_플랩", "base_key": "솔티커튼_리지", "ad_id": "120248695560010667", "objective": "전환", "pa_type": "자컨", "landing": "플랩", "purpose": "전환", "mgr": "리지", "media": "영상", "spend": 74700, "impressions": 3031, "clicks": 102, "purchases": 2.0, "revenue": 379000, "age_days": 3, "roas": 5.073628, "roas_pct": 507.0, "ctr": 3.37, "cvr": 1.96, "cpc": 732.0, "is_new": true, "old_roas_pct": 507.0, "roas_delta": 0.0, "prev_spend": 74700, "prev_ctr": 3.37, "prev_cvr": 1.96, "prev_cpc": 732.0, "prev_purchases": 2, "prev_revenue": 379000, "img": "https://www.facebook.com/ads/image/?d=AQJ4hTXXoZkDb6wl6rESk1KTA5IYfwLBkTx-aEKOe30cqv9aXG6_e9wIoLkpCg0Ln8g1uLZSp4xxPBuQOCOWxS2W1a5i1Exdp6rPHrvddeYfVRrdld0XMdp8cPAXkYcURctLf9avj6mEV69mT2Oi70FL", "img_type": "video", "video": "977776271612775", "win_score": null, "win_type": null, "win_flags": {}}, {"key": "전환_브랜디드_콜리_플랩", "base_key": "브랜디드_콜리", "ad_id": "120242899546890667", "objective": "전환", "pa_type": "자컨", "landing": "플랩", "purpose": "전환", "mgr": "콜리", "media": "영상", "spend": 66490, "impressions": 1717, "clicks": 48, "purchases": 0, "revenue": 0, "age_days": 107, "roas": 0, "roas_pct": 0, "ctr": 2.8, "cvr": 0.0, "cpc": 1385.0, "is_new": false, "old_roas_pct": null, "roas_delta": null, "prev_spend": 66490, "prev_ctr": 2.8, "prev_cvr": null, "prev_cpc": 1385.0, "prev_purchases": null, "prev_revenue": null, "img": "https://www.facebook.com/ads/image/?d=AQK64-o4yQRyiwk4FxAJJnBzE__D95S1TMDAot6fmkFjKF6j5zCJs6y1IQzkIxuCo_rswOIu3LSZ-My5vWIvbOpvy0kk9Ocu0zvwY586FNcQZ54JGXsPt0umVFQHKmhSeiJOcdoaV5AwBTu1VqLaVHPl", "img_type": "video", "video": "1411466354047130", "win_score": null, "win_type": null, "win_flags": {}}, {"key": "전환_바퀴2_콜리_오딧", "base_key": "바퀴2_콜리", "ad_id": "120246084324830667", "objective": "전환", "pa_type": "자컨", "landing": "오딧", "purpose": "전환", "mgr": "콜리", "media": "영상", "spend": 58833, "impressions": 1869, "clicks": 19, "purchases": 0, "revenue": 0, "age_days": 44, "roas": 0, "roas_pct": 0, "ctr": 1.02, "cvr": 0.0, "cpc": 3096.0, "is_new": false, "old_roas_pct": null, "roas_delta": null, "prev_spend": 58833, "prev_ctr": 1.02, "prev_cvr": null, "prev_cpc": 3096.0, "prev_purchases": null, "prev_revenue": null, "img": "https://scontent-sin6-1.xx.fbcdn.net/v/t45.1600-4/656719502_122105118753123564_4474784661276945910_n.png?stp=dst-jpg_tt6&_nc_cat=111&ccb=1-7&_nc_sid=d5bd00&_nc_ohc=hlOS4R9u8yIQ7kNvwEkzfRN&_nc_oc=Adp4hy6BESGjWaoxQCDeb7Blq_g5Mz-UJ2CaTruGlx51uFAyWuzmR68lp80uCLuAKYE&_nc_zt=1&_nc_ht=scontent-sin6-1.xx&edm=AAwGEdEEAAAA&_nc_gid=0jjXs1f1YGlbj5sX_Y3Slw&_nc_tpa=Q5bMBQG0_Fc6NERkL9NrKTlMHMkVQ3mO7SMo0MiCGlfD-Ymxs0weyx63DKQ6VUVdARMxbnTiO0TKVme6Jw&oh=00_Af-5fiXjuNDqxJRsXaB6GhqmXLWEuVrbCiOSfpeaqbLSgw&oe=6A36DFE4", "img_type": "img", "video": null, "win_score": null, "win_type": null, "win_flags": {}}, {"key": "전환_작누댁2차활용_05디벨롭_세레나_오딧", "base_key": "작누댁2차활용_05디벨롭_세레나", "ad_id": "120247734527080667", "objective": "전환", "pa_type": "자컨", "landing": "오딧", "purpose": "전환", "mgr": "세레나", "media": "영상", "spend": 58726, "impressions": 2222, "clicks": 97, "purchases": 1.0, "revenue": 310000, "age_days": 18, "roas": 5.278752, "roas_pct": 528.0, "ctr": 4.37, "cvr": 1.03, "cpc": 605.0, "is_new": false, "old_roas_pct": 528.0, "roas_delta": 0.0, "prev_spend": 58726, "prev_ctr": 4.37, "prev_cvr": 1.03, "prev_cpc": 605.0, "prev_purchases": 1, "prev_revenue": 310000, "img": "https://www.facebook.com/ads/image/?d=AQJJt6uJ5WB90QNKn4NLem1jQ--dFsIxhuMi2lId4fD--yxdB7tm6rgXlUlAl-N4A_vxnIWjKoScOTORdtqU4VnzSruLjCxKqH6i2Bz2DoFV9TuQxnmJ1LIuYNZVOHT5jOC5X2SfEMLbjHeOvD5PmPap", "img_type": "video", "video": "2143031509880542", "win_score": null, "win_type": null, "win_flags": {}}, {"key": "전환_수납1_세레나_플랩", "base_key": "수납1_세레나", "ad_id": "120246067677820667", "objective": "전환", "pa_type": "자컨", "landing": "플랩", "purpose": "전환", "mgr": "세레나", "media": "영상", "spend": 51651, "impressions": 1862, "clicks": 65, "purchases": 2.0, "revenue": 1211400, "age_days": 44, "roas": 23.453563, "roas_pct": 2345.0, "ctr": 3.49, "cvr": 3.08, "cpc": 795.0, "is_new": false, "old_roas_pct": 2345.0, "roas_delta": 0.0, "prev_spend": 51651, "prev_ctr": 3.49, "prev_cvr": 3.08, "prev_cpc": 795.0, "prev_purchases": 2, "prev_revenue": 1211400, "img": "https://www.facebook.com/ads/image/?d=AQJb4qfaftscQdq1Ws1M7IPYdE9-_Fe1hd9Qsx7I3qOPxGfO87DOplKWsJYI0evdQPkDRxVWk-ObbExFk9ykWuhDJBowO-fiXO868O4hI9nyaPeDbquSjbMC5sroRB0ZqqrCnFF116WuKf90grbu_DAX", "img_type": "video", "video": "1556163542153836", "win_score": null, "win_type": null, "win_flags": {}}, {"key": "전환_26인치_재입고04_콜리_오딧", "base_key": "26인치_재입고04_콜리", "ad_id": "120248577076980667", "objective": "전환", "pa_type": "자컨", "landing": "오딧", "purpose": "전환", "mgr": "콜리", "media": "배너", "spend": 37837, "impressions": 1648, "clicks": 46, "purchases": 1.0, "revenue": 350000, "age_days": 4, "roas": 9.250205, "roas_pct": 925.0, "ctr": 2.79, "cvr": 2.17, "cpc": 823.0, "is_new": true, "old_roas_pct": 925.0, "roas_delta": 0.0, "prev_spend": 37837, "prev_ctr": 2.79, "prev_cvr": 2.17, "prev_cpc": 823.0, "prev_purchases": 1, "prev_revenue": 350000, "img": "https://scontent-sin11-1.xx.fbcdn.net/v/t45.1600-4/686449651_122111127357123564_3147507027285960397_n.png?stp=dst-jpg_tt6&_nc_cat=104&ccb=1-7&_nc_sid=d5bd00&_nc_ohc=PmefB2MUym0Q7kNvwF-7NM7&_nc_oc=AdpdXbNSSdak9lfLxB_x567uVvIXY30vQmmrhnOrJUg9swWIwlQ3Xv7J7CMQLyD1Ljo&_nc_zt=1&_nc_ht=scontent-sin11-1.xx&edm=AAwGEdEEAAAA&_nc_gid=sM8-hd7zmr8WaZwsQncXBA&_nc_tpa=Q5bMBQG9HxJPiOSUMpito0WP8yXp4LYLR-z3bERu855kOkiAvbwho3uTgdLHsAGmacg6UrXzbSQOtGta3Q&oh=00_Af_bmz21FpikpZZq6FzT-RoxiJBkwEph1HsDPbnnj89o6g&oe=6A36D519", "img_type": "img", "video": null, "win_score": null, "win_type": null, "win_flags": {}}, {"key": "전환_플랩리뷰01_콜리_플랩", "base_key": "플랩리뷰01_콜리", "ad_id": "120247091199850667", "objective": "전환", "pa_type": "자컨", "landing": "플랩", "purpose": "전환", "mgr": "콜리", "media": "배너", "spend": 35459, "impressions": 2177, "clicks": 47, "purchases": 2.0, "revenue": 625000, "age_days": 31, "roas": 17.625991, "roas_pct": 1763.0, "ctr": 2.16, "cvr": 4.26, "cpc": 754.0, "is_new": false, "old_roas_pct": 1763.0, "roas_delta": 0.0, "prev_spend": 35459, "prev_ctr": 2.16, "prev_cvr": 4.26, "prev_cpc": 754.0, "prev_purchases": 2, "prev_revenue": 625000, "img": "https://scontent-sin11-1.xx.fbcdn.net/v/t45.1600-4/662509806_122106567213123564_2387757775234709850_n.png?stp=dst-jpg_tt6&_nc_cat=104&ccb=1-7&_nc_sid=d5bd00&_nc_ohc=i2aRM3XgpGMQ7kNvwED0sZz&_nc_oc=AdrH5hnkYH7FWQwtAGyUlQRcNbyPnek6tBEpQbEKLFJOJP0DnVpG5DBfuXGjsZw9B-o&_nc_zt=1&_nc_ht=scontent-sin11-1.xx&edm=AAwGEdEEAAAA&_nc_gid=wL0INJYirGfaoqSFQ807ww&_nc_tpa=Q5bMBQH7unH8c5N3eEfIKQf7PBdy6fWtY9XVMMWVfSObW4pz24XKwk94VFYKvuLZP7UveqIc76NRzWv6zQ&oh=00_Af_o8GrlRfiOC66pLyJKwwRzttPxOKAXxye75-Bma-7Fug&oe=6A36FF1B", "img_type": "img", "video": null, "win_score": null, "win_type": null, "win_flags": {}}, {"key": "전환_경사로_01_리지_플랩", "base_key": "경사로_01_리지", "ad_id": "120248233077280667", "objective": "전환", "pa_type": "자컨", "landing": "플랩", "purpose": "전환", "mgr": "리지", "media": "영상", "spend": 28872, "impressions": 916, "clicks": 31, "purchases": 2.0, "revenue": 1010000, "age_days": 10, "roas": 34.981989, "roas_pct": 3498.0, "ctr": 3.38, "cvr": 6.45, "cpc": 931.0, "is_new": false, "old_roas_pct": 3498.0, "roas_delta": 0.0, "prev_spend": 28872, "prev_ctr": 3.38, "prev_cvr": 6.45, "prev_cpc": 931.0, "prev_purchases": 2, "prev_revenue": 1010000, "img": "https://www.facebook.com/ads/image/?d=AQIp5JiFIymCQQmtonR1CFcMdDYAc4JUqrnn42F16OU1R7lElLQDqBqfF1etfFcR2wAPIyXKMR5p4Wlx5rd-Y7_F_RmvgjFXoYdmmGLGOngdv7538j-8J_X_s7DHXjV8U78jImt8vG0mT31snZ6lzOfW", "img_type": "video", "video": "2172882746858467", "win_score": null, "win_type": null, "win_flags": {}}, {"key": "전환_솔티커튼02_리지_플랩", "base_key": "솔티커튼02_리지", "ad_id": "120248695560020667", "objective": "전환", "pa_type": "자컨", "landing": "플랩", "purpose": "전환", "mgr": "리지", "media": "영상", "spend": 27621, "impressions": 989, "clicks": 32, "purchases": 0, "revenue": 0, "age_days": 3, "roas": 0, "roas_pct": 0, "ctr": 3.24, "cvr": 0.0, "cpc": 863.0, "is_new": true, "old_roas_pct": null, "roas_delta": null, "prev_spend": 27621, "prev_ctr": 3.24, "prev_cvr": null, "prev_cpc": 863.0, "prev_purchases": null, "prev_revenue": null, "img": "https://www.facebook.com/ads/image/?d=AQJKs7rc4dlTZpdiwEdHGzb-Rbca1Eefv0qtDt93aY-rNFkmCSVFrHzQB8zKY3VwmQrNbqC-5cqxEuQiVW1KUv1HHi4mqyeqfj91yT0-lTB6XPOf-P_Ex5JYpRKAFN-kVT5-WXNEWMd1Ge8q4kW8AVhW", "img_type": "video", "video": "1831255254509486", "win_score": null, "win_type": null, "win_flags": {}}, {"key": "전환_파트너스_59SEOK_플랩", "base_key": "파트너스_59SEOK", "ad_id": "120247333343220667", "objective": "전환", "pa_type": "PA", "landing": "플랩", "purpose": "전환", "mgr": "파트너스", "media": "영상", "spend": 27555, "impressions": 1456, "clicks": 38, "purchases": 0, "revenue": 0, "age_days": 23, "roas": 0, "roas_pct": 0, "ctr": 2.61, "cvr": 0.0, "cpc": 725.0, "is_new": false, "old_roas_pct": null, "roas_delta": null, "prev_spend": 27555, "prev_ctr": 2.61, "prev_cvr": null, "prev_cpc": 725.0, "prev_purchases": null, "prev_revenue": null, "img": null, "img_type": "video", "video": "36010752971845163", "win_score": null, "win_type": null, "win_flags": {}}, {"key": "전환_작누댁2차활용_07-2_세레나_오딧", "base_key": "작누댁2차활용_07-2_세레나", "ad_id": "120248582841450667", "objective": "전환", "pa_type": "자컨", "landing": "오딧", "purpose": "전환", "mgr": "세레나", "media": "영상", "spend": 27451, "impressions": 854, "clicks": 28, "purchases": 1.0, "revenue": 640000, "age_days": 4, "roas": 23.314269, "roas_pct": 2331.0, "ctr": 3.28, "cvr": 3.57, "cpc": 980.0, "is_new": true, "old_roas_pct": 2331.0, "roas_delta": 0.0, "prev_spend": 27451, "prev_ctr": 3.28, "prev_cvr": 3.57, "prev_cpc": 980.0, "prev_purchases": 1, "prev_revenue": 640000, "img": "https://www.facebook.com/ads/image/?d=AQJx8k83wYyT-JEUoXpqbCBLEW7Z75RG8JswSwEVBvyJ3wBNNlzXUuDyuiVZueQ6-Lo6CZcrlyFCSHK72tAzpUYIRru4L-yMUChpjxZC5fvxcveeKwJN8djscjaT72GF1JMQ80TEBzSuDWVMvgBmZ90-", "img_type": "video", "video": "1315200740793526", "win_score": null, "win_type": null, "win_flags": {}}, {"key": "전환_파트너스_차성빈_플랩", "base_key": "파트너스_차성빈", "ad_id": "120244300702180667", "objective": "전환", "pa_type": "PA", "landing": "플랩", "purpose": "전환", "mgr": "파트너스", "media": "영상", "spend": 27118, "impressions": 1263, "clicks": 21, "purchases": 1.0, "revenue": 295000, "age_days": 76, "roas": 10.878383, "roas_pct": 1088.0, "ctr": 1.66, "cvr": 4.76, "cpc": 1291.0, "is_new": false, "old_roas_pct": 1088.0, "roas_delta": 0.0, "prev_spend": 27118, "prev_ctr": 1.66, "prev_cvr": 4.76, "prev_cpc": 1291.0, "prev_purchases": 1, "prev_revenue": 295000, "img": null, "img_type": "video", "video": "1807760926573358", "win_score": null, "win_type": null, "win_flags": {}}, {"key": "전환_지혜사랑2차활용_07-1_세레나_오딧", "base_key": "지혜사랑2차활용_07-1_세레나", "ad_id": "120248681555650667", "objective": "전환", "pa_type": "자컨", "landing": "오딧", "purpose": "전환", "mgr": "세레나", "media": "영상", "spend": 26794, "impressions": 1099, "clicks": 31, "purchases": 0, "revenue": 0, "age_days": 3, "roas": 0, "roas_pct": 0, "ctr": 2.82, "cvr": 0.0, "cpc": 864.0, "is_new": true, "old_roas_pct": null, "roas_delta": null, "prev_spend": 26794, "prev_ctr": 2.82, "prev_cvr": null, "prev_cpc": 864.0, "prev_purchases": null, "prev_revenue": null, "img": "https://www.facebook.com/ads/image/?d=AQL1MxTJcJfUOQc3K0qctfnUv0xzTRwu7zHOuqLjnblEMCRgvmegTDDtQHI5Xbdq3n3VFUJq9FmaJ-gR2EGOU68ER-ibDcYf3t0VbLoBjm2llLKeUNJcrfVP0rWPMhfIVAFf44tCXDPj9hf4_aeU0y8h", "img_type": "video", "video": "974683224933644", "win_score": null, "win_type": null, "win_flags": {}}, {"key": "전환_경사로_02_리지_플랩", "base_key": "경사로_02_리지", "ad_id": "120248233077290667", "objective": "전환", "pa_type": "자컨", "landing": "플랩", "purpose": "전환", "mgr": "리지", "media": "영상", "spend": 25843, "impressions": 658, "clicks": 21, "purchases": 0, "revenue": 0, "age_days": 10, "roas": 0, "roas_pct": 0, "ctr": 3.19, "cvr": 0.0, "cpc": 1231.0, "is_new": false, "old_roas_pct": null, "roas_delta": null, "prev_spend": 25843, "prev_ctr": 3.19, "prev_cvr": null, "prev_cpc": 1231.0, "prev_purchases": null, "prev_revenue": null, "img": "https://www.facebook.com/ads/image/?d=AQLiUZ23ua9qn8hQbCwNU5mTBrI9U5R6XTesDF0tF0XbDmcJbYpPek0P6WyLTWuPL8Mq4QzBd11HylBqqLVz5x6tCtjRFgoSVqjJtgEtmJG0zyWjkjcwU86-4EZrZtoD-y3G_1WOo6kJw2m5OSR_z_wn", "img_type": "video", "video": "953679723934809", "win_score": null, "win_type": null, "win_flags": {}}, {"key": "전환_바퀴1_콜리_오딧", "base_key": "바퀴1_콜리", "ad_id": "120246084324820667", "objective": "전환", "pa_type": "자컨", "landing": "오딧", "purpose": "전환", "mgr": "콜리", "media": "영상", "spend": 24026, "impressions": 777, "clicks": 14, "purchases": 0, "revenue": 0, "age_days": 44, "roas": 0, "roas_pct": 0, "ctr": 1.8, "cvr": 0.0, "cpc": 1716.0, "is_new": false, "old_roas_pct": null, "roas_delta": null, "prev_spend": 24026, "prev_ctr": 1.8, "prev_cvr": null, "prev_cpc": 1716.0, "prev_purchases": null, "prev_revenue": null, "img": "https://scontent-sin11-2.xx.fbcdn.net/v/t45.1600-4/656071551_122105118717123564_8490462013199139282_n.png?stp=dst-jpg_tt6&_nc_cat=108&ccb=1-7&_nc_sid=d5bd00&_nc_ohc=bqFyrSIFlYkQ7kNvwH8tQPR&_nc_oc=AdqHSWvJoyC6WuOCAef6Dl4G-2vJ3Z9bA9S6yDTSuFrmDo3gjWxfigL_wP30O7RdDy8&_nc_zt=1&_nc_ht=scontent-sin11-2.xx&edm=AAwGEdEEAAAA&_nc_gid=ejEwCI5iDAxtHScdkkOBiw&_nc_tpa=Q5bMBQFZTPAuPtXLkXVSd34l9YFqKXbqaZ512n5cjECPEkBDZViIqfAAOrMaV3VDY9iMO4-Dj0xyIL4y6Q&oh=00_Af-6aXaBPAwR5Twi2YbPiTQImA835pQLVtBKxpPJLJAh4A&oe=6A36F7B9", "img_type": "img", "video": null, "win_score": null, "win_type": null, "win_flags": {}}, {"key": "전환_솔티블루_콜리_오딧", "base_key": "솔티블루_콜리", "ad_id": "120245722173600667", "objective": "전환", "pa_type": "자컨", "landing": "오딧", "purpose": "전환", "mgr": "콜리", "media": "영상", "spend": 19241, "impressions": 712, "clicks": 33, "purchases": 0, "revenue": 0, "age_days": 51, "roas": 0, "roas_pct": 0, "ctr": 4.63, "cvr": 0.0, "cpc": 583.0, "is_new": false, "old_roas_pct": null, "roas_delta": null, "prev_spend": 19241, "prev_ctr": 4.63, "prev_cvr": null, "prev_cpc": 583.0, "prev_purchases": null, "prev_revenue": null, "img": "https://www.facebook.com/ads/image/?d=AQJDS-D3qlNrKTDnt-fE-JVYCCvZV2T1xJg_e_MSOccQb1bDmvypcwu2vnvCX2EaB2Qrxp5ZoYwMDCqY6pkFvVYu8D_e2dyujnY77hzH9Us_kjMnn8QYBxLyqfZ3tL6IDnitcr_nLkCKhVee8Y5aV2zh", "img_type": "video", "video": "2379984482465484", "win_score": null, "win_type": null, "win_flags": {}}, {"key": "전환__hyerimood__대세감01_세레나_플랩", "base_key": "_hyerimood__대세감01_세레나", "ad_id": "120247091199870667", "objective": "전환", "pa_type": "자컨", "landing": "플랩", "purpose": "전환", "mgr": "세레나", "media": "영상", "spend": 12576, "impressions": 428, "clicks": 12, "purchases": 0, "revenue": 0, "age_days": 31, "roas": 0, "roas_pct": 0, "ctr": 2.8, "cvr": 0.0, "cpc": 1048.0, "is_new": false, "old_roas_pct": null, "roas_delta": null, "prev_spend": 12576, "prev_ctr": 2.8, "prev_cvr": null, "prev_cpc": 1048.0, "prev_purchases": null, "prev_revenue": null, "img": "https://scontent-sin6-1.xx.fbcdn.net/v/t45.1600-4/670262969_122117309211225536_5238399339839743732_n.png?stp=dst-jpg_tt6&_nc_cat=111&ccb=1-7&_nc_sid=d5bd00&_nc_ohc=HGKMtedxWqsQ7kNvwF0NXgO&_nc_oc=AdreIw-uiD1vcqyJB_zgLaHxSIuF9M-ehCSCrsprV_b6w17IM5hYY-eiyk3rZau3jy8&_nc_zt=1&_nc_ht=scontent-sin6-1.xx&edm=AAwGEdEEAAAA&_nc_gid=jgohesW6AdyHleXJBHVJlg&_nc_tpa=Q5bMBQHntyAq8gKmoPfaE-kACyHkZF1Pg1EmYvREdddcHVRT7LyOGR9rCkev1s0wv4v7NVhwVjjl_r7o8A&oh=00_Af_fRaF1Szi_gJT1qttJhKBWgvwZKvvgJeLWwTjKfB5nEQ&oe=6A36D9AC", "img_type": "img", "video": null, "win_score": null, "win_type": null, "win_flags": {}}, {"key": "전환_5월연휴06_세레나_오딧", "base_key": "5월연휴06_세레나", "ad_id": "120248001875570667", "objective": "전환", "pa_type": "자컨", "landing": "오딧", "purpose": "전환", "mgr": "세레나", "media": "영상", "spend": 12445, "impressions": 497, "clicks": 7, "purchases": 2.0, "revenue": 740000, "age_days": 13, "roas": 59.461631, "roas_pct": 5946.0, "ctr": 1.41, "cvr": 28.57, "cpc": 1778.0, "is_new": false, "old_roas_pct": 5946.0, "roas_delta": 0.0, "prev_spend": 12445, "prev_ctr": 1.41, "prev_cvr": 28.57, "prev_cpc": 1778.0, "prev_purchases": 2, "prev_revenue": 740000, "img": null, "img_type": "img", "video": null, "win_score": null, "win_type": null, "win_flags": {}}, {"key": "전환_솔티블루리뷰_콜리_오딧", "base_key": "솔티블루리뷰_콜리", "ad_id": "120247747557520667", "objective": "전환", "pa_type": "자컨", "landing": "오딧", "purpose": "전환", "mgr": "콜리", "media": "영상", "spend": 12213, "impressions": 362, "clicks": 14, "purchases": 0, "revenue": 0, "age_days": 16, "roas": 0, "roas_pct": 0, "ctr": 3.87, "cvr": 0.0, "cpc": 872.0, "is_new": false, "old_roas_pct": null, "roas_delta": null, "prev_spend": 12213, "prev_ctr": 3.87, "prev_cvr": null, "prev_cpc": 872.0, "prev_purchases": null, "prev_revenue": null, "img": null, "img_type": "img", "video": null, "win_score": null, "win_type": null, "win_flags": {}}, {"key": "전환_챈미2차활용_04_세레나_오딧", "base_key": "챈미2차활용_04_세레나", "ad_id": "120247605912530667", "objective": "전환", "pa_type": "자컨", "landing": "오딧", "purpose": "전환", "mgr": "세레나", "media": "영상", "spend": 12012, "impressions": 407, "clicks": 16, "purchases": 1.0, "revenue": 669500, "age_days": 18, "roas": 55.735931, "roas_pct": 5574.0, "ctr": 3.93, "cvr": 6.25, "cpc": 751.0, "is_new": false, "old_roas_pct": 5574.0, "roas_delta": 0.0, "prev_spend": 12012, "prev_ctr": 3.93, "prev_cvr": 6.25, "prev_cpc": 751.0, "prev_purchases": 1, "prev_revenue": 669500, "img": "https://www.facebook.com/ads/image/?d=AQKVqcsxe1pqpH2sBIBimW8aO3gufwRBpunrmRF4Om-d7iklVXHvYzFYYN9rPUwaGozPCLVS8WS7g2Png2ZyHJlUSr3q4ll5FmT-IJzx_s32o6QNSL8KZNTnvMCzsODw97nxlWOJAhP7mL8DKRlxKIc2", "img_type": "video", "video": "986790070966045", "win_score": null, "win_type": null, "win_flags": {}}, {"key": "전환_나문_리지_플랩", "base_key": "나문_리지", "ad_id": "120248695838670667", "objective": "전환", "pa_type": "자컨", "landing": "플랩", "purpose": "전환", "mgr": "리지", "media": "배너", "spend": 11981, "impressions": 392, "clicks": 14, "purchases": 0, "revenue": 0, "age_days": 3, "roas": 0, "roas_pct": 0, "ctr": 3.57, "cvr": 0.0, "cpc": 856.0, "is_new": true, "old_roas_pct": null, "roas_delta": null, "prev_spend": 11981, "prev_ctr": 3.57, "prev_cvr": null, "prev_cpc": 856.0, "prev_purchases": null, "prev_revenue": null, "img": "https://scontent-sin6-3.xx.fbcdn.net/v/t45.1600-4/686519547_122101478781297071_1281293149747597168_n.png?stp=dst-jpg_tt6&_nc_cat=106&ccb=1-7&_nc_sid=d5bd00&_nc_ohc=Dg7rQP12yd8Q7kNvwFDenTj&_nc_oc=AdqpY1ejgpbAWhygbEvcOJUXOhOLOgL66RiVj8RY9pRTTTXDvMxn-0o6dREFKQZZC2Q&_nc_zt=1&_nc_ht=scontent-sin6-3.xx&edm=AAwGEdEEAAAA&_nc_gid=5ICExK8XqStHcUuIBXJ8Kw&_nc_tpa=Q5bMBQEIRbcLei6Q8BnKhWXSRqFO3hFOl7PnFwtrRWLmvFpcS4dnCm9LJsrK8dkKNBbMg6eMEJ-rQj3SJA&oh=00_Af_jxXtZCWHW3q8eZ3p7Zr27rUU9bc9CYNPImeTm65Ft9A&oe=6A36F05E", "img_type": "img", "video": null, "win_score": null, "win_type": null, "win_flags": {}}, {"key": "전환_플랩리뷰02__sunheekimm_콜리_플랩", "base_key": "플랩리뷰02__sunheekimm_콜리", "ad_id": "120247091199900667", "objective": "전환", "pa_type": "자컨", "landing": "플랩", "purpose": "전환", "mgr": "콜리", "media": "배너", "spend": 11053, "impressions": 394, "clicks": 9, "purchases": 1.0, "revenue": 330000, "age_days": 31, "roas": 29.856148, "roas_pct": 2986.0, "ctr": 2.28, "cvr": 11.11, "cpc": 1228.0, "is_new": false, "old_roas_pct": 2986.0, "roas_delta": 0.0, "prev_spend": 11053, "prev_ctr": 2.28, "prev_cvr": 11.11, "prev_cpc": 1228.0, "prev_purchases": 1, "prev_revenue": 330000, "img": null, "img_type": "img", "video": null, "win_score": null, "win_type": null, "win_flags": {}}, {"key": "전환_챈미2차활용_07_세레나_오딧", "base_key": "챈미2차활용_07_세레나", "ad_id": "120247952636550667", "objective": "전환", "pa_type": "자컨", "landing": "오딧", "purpose": "전환", "mgr": "세레나", "media": "영상", "spend": 10405, "impressions": 350, "clicks": 10, "purchases": 0, "revenue": 0, "age_days": 13, "roas": 0, "roas_pct": 0, "ctr": 2.86, "cvr": 0.0, "cpc": 1040.0, "is_new": false, "old_roas_pct": null, "roas_delta": null, "prev_spend": 10405, "prev_ctr": 2.86, "prev_cvr": null, "prev_cpc": 1040.0, "prev_purchases": null, "prev_revenue": null, "img": "https://www.facebook.com/ads/image/?d=AQIJBNXqGz2IRiY1ZwQe2QQfm4IDqPTXg6qoFg6FdVsTNrrQ65DOLR3wnKThRzddhwQJMuqjDZNnbBqhHRwjQUYpKNG0oEIBkkfI7K_ofJZ_2x9tWYALGDEwsWh4kcmGBOZPuK8RjhadEuKHpwuJvUBb", "img_type": "video", "video": "948903874533683", "win_score": null, "win_type": null, "win_flags": {}}, {"key": "전환_트렁크_리지_플랩", "base_key": "트렁크_리지", "ad_id": "120248232458010667", "objective": "전환", "pa_type": "자컨", "landing": "플랩", "purpose": "전환", "mgr": "리지", "media": "영상", "spend": 7760, "impressions": 427, "clicks": 15, "purchases": 0, "revenue": 0, "age_days": 10, "roas": 0, "roas_pct": 0, "ctr": 3.51, "cvr": 0.0, "cpc": 517.0, "is_new": false, "old_roas_pct": null, "roas_delta": null, "prev_spend": 7760, "prev_ctr": 3.51, "prev_cvr": null, "prev_cpc": 517.0, "prev_purchases": null, "prev_revenue": null, "img": "https://www.facebook.com/ads/image/?d=AQJYsiIR97v89c8aUiOrYr0A5wDkWDtsiahhmHnyhsXG3jJ2nc_cUaEKy0nWfH9Fb7zuunS_2adMVaNH8mlySakDTEqVnLOf8ZgSoJEkamL7K5Mu7tuFXld9HwtsfND2l50eYtJ0f3GlltLowvB5OZ3V", "img_type": "video", "video": "2202173563920280", "win_score": null, "win_type": null, "win_flags": {}}, {"key": "전환_작누댁2차활용_07-3_세레나_오딧", "base_key": "작누댁2차활용_07-3_세레나", "ad_id": "120248582841440667", "objective": "전환", "pa_type": "자컨", "landing": "오딧", "purpose": "전환", "mgr": "세레나", "media": "영상", "spend": 7695, "impressions": 218, "clicks": 4, "purchases": 1.0, "revenue": 350000, "age_days": 4, "roas": 45.484081, "roas_pct": 4548.0, "ctr": 1.83, "cvr": 25.0, "cpc": 1924.0, "is_new": true, "old_roas_pct": 4548.0, "roas_delta": 0.0, "prev_spend": 7695, "prev_ctr": 1.83, "prev_cvr": 25.0, "prev_cpc": 1924.0, "prev_purchases": 1, "prev_revenue": 350000, "img": "https://www.facebook.com/ads/image/?d=AQKmt30naz6ZUi-rYqWXB08SfMYXf18j_W1z8ZiBBs8kuNKU5I8ijzDVw9F-Weofbheujvoz45uRr381IXiKFQOyzRePl2M2D5oaR6VFYEexoXIew_s-97DLq48MMlzg9YMYVD8VBgfTvsQMY0ZPHQAW", "img_type": "video", "video": "1752925469205538", "win_score": null, "win_type": null, "win_flags": {}}, {"key": "전환_플랩리뷰03_baebaelee___콜리_플랩", "base_key": "플랩리뷰03_baebaelee___콜리", "ad_id": "120247091199910667", "objective": "전환", "pa_type": "자컨", "landing": "플랩", "purpose": "전환", "mgr": "콜리", "media": "배너", "spend": 6276, "impressions": 295, "clicks": 8, "purchases": 0, "revenue": 0, "age_days": 31, "roas": 0, "roas_pct": 0, "ctr": 2.71, "cvr": 0.0, "cpc": 784.0, "is_new": false, "old_roas_pct": null, "roas_delta": null, "prev_spend": 6276, "prev_ctr": 2.71, "prev_cvr": null, "prev_cpc": 784.0, "prev_purchases": null, "prev_revenue": null, "img": null, "img_type": "img", "video": null, "win_score": null, "win_type": null, "win_flags": {}}, {"key": "전환_26인치_재입고03-1_콜리_오딧", "base_key": "26인치_재입고03-1_콜리", "ad_id": "120248577076960667", "objective": "전환", "pa_type": "자컨", "landing": "오딧", "purpose": "전환", "mgr": "콜리", "media": "배너", "spend": 5419, "impressions": 193, "clicks": 3, "purchases": 0, "revenue": 0, "age_days": 4, "roas": 0, "roas_pct": 0, "ctr": 1.55, "cvr": 0.0, "cpc": 1806.0, "is_new": true, "old_roas_pct": null, "roas_delta": null, "prev_spend": 5419, "prev_ctr": 1.55, "prev_cvr": null, "prev_cpc": 1806.0, "prev_purchases": null, "prev_revenue": null, "img": "https://scontent-sin6-3.xx.fbcdn.net/v/t45.1600-4/684165312_122111127309123564_6825903961329983095_n.png?stp=dst-jpg_tt6&_nc_cat=106&ccb=1-7&_nc_sid=d5bd00&_nc_ohc=Rtc5xEWFoZQQ7kNvwG6SE71&_nc_oc=AdpbN6xyzefAldOj9NkKP7sNcqJXqDGsaYUT4vRWcUpbQ4yDPHl1isFmu47AGR12XLg&_nc_zt=1&_nc_ht=scontent-sin6-3.xx&edm=AAwGEdEEAAAA&_nc_gid=S44nazryteIP_jZusY6b6w&_nc_tpa=Q5bMBQHOQ2f9WvLpEH-Kxk5uvFaitQsSDSLoDTCP0U9eiRQfdj40lKI2JPnkzr9kq7GmM4IptOqqHP3R0A&oh=00_Af_MLYkF9eGZDw-vivAhWcuacdVXYxdKTL95CYhajb3znw&oe=6A36F2E3", "img_type": "img", "video": null, "win_score": null, "win_type": null, "win_flags": {}}, {"key": "전환_지혜사랑2차활용_07-2_세레나_오딧", "base_key": "지혜사랑2차활용_07-2_세레나", "ad_id": "120248681555660667", "objective": "전환", "pa_type": "자컨", "landing": "오딧", "purpose": "전환", "mgr": "세레나", "media": "영상", "spend": 5097, "impressions": 136, "clicks": 13, "purchases": 1.0, "revenue": 845400, "age_days": 3, "roas": 165.862272, "roas_pct": 16586.0, "ctr": 9.56, "cvr": 7.69, "cpc": 392.0, "is_new": true, "old_roas_pct": 16586.0, "roas_delta": 0.0, "prev_spend": 5097, "prev_ctr": 9.56, "prev_cvr": 7.69, "prev_cpc": 392.0, "prev_purchases": 1, "prev_revenue": 845400, "img": "https://www.facebook.com/ads/image/?d=AQK5eo7qTuyndVW37onPk8yun1YJ0q_vUv0U8ZSmRM7L7Am9AZmV4DBoUc3ptCrGwJuWrpPws8wzV5c4x1Y4P2dnrnR8R5otOnh7z8Q7RiArNwH1IUPxtEl66g5xSibKefYubfR6GO9dOkNf9TWqTyIM", "img_type": "video", "video": "1398778202247163", "win_score": null, "win_type": null, "win_flags": {}}, {"key": "전환_작누댁2차활용_04디벨롭01_세레나_오딧", "base_key": "작누댁2차활용_04디벨롭01_세레나", "ad_id": "120247734527100667", "objective": "전환", "pa_type": "자컨", "landing": "오딧", "purpose": "전환", "mgr": "세레나", "media": "영상", "spend": 4702, "impressions": 140, "clicks": 16, "purchases": 2.0, "revenue": 1760000, "age_days": 18, "roas": 374.308805, "roas_pct": 37431.0, "ctr": 11.43, "cvr": 12.5, "cpc": 294.0, "is_new": false, "old_roas_pct": 37431.0, "roas_delta": 0.0, "prev_spend": 4702, "prev_ctr": 11.43, "prev_cvr": 12.5, "prev_cpc": 294.0, "prev_purchases": 2, "prev_revenue": 1760000, "img": "https://www.facebook.com/ads/image/?d=AQISlA7aqRXHOk5jdHNvlWdHKkrkwzO56T7uADPcE92hdn39fwWVXTabymeo27wDccgH1cEqZzygYSlmy_sN7ZbMizyCKfZpx7z1vbXRwyvSza-MSOf5FDQ-k_RXOZuuitonn3cMcGUa_3-_qPcifYxG", "img_type": "video", "video": "850052597368889", "win_score": null, "win_type": null, "win_flags": {}}, {"key": "전환_지혜사랑2차활용_07-3_세레나_오딧", "base_key": "지혜사랑2차활용_07-3_세레나", "ad_id": "120248681555630667", "objective": "전환", "pa_type": "자컨", "landing": "오딧", "purpose": "전환", "mgr": "세레나", "media": "영상", "spend": 4581, "impressions": 260, "clicks": 11, "purchases": 0, "revenue": 0, "age_days": 3, "roas": 0, "roas_pct": 0, "ctr": 4.23, "cvr": 0.0, "cpc": 416.0, "is_new": true, "old_roas_pct": null, "roas_delta": null, "prev_spend": 4581, "prev_ctr": 4.23, "prev_cvr": null, "prev_cpc": 416.0, "prev_purchases": null, "prev_revenue": null, "img": "https://www.facebook.com/ads/image/?d=AQKhI79u-rOWNyrbdPU2eX4U46W9dMb_s-8pdld95KyZBjQf4NyJW8WUoKYWxaOVbxx27fQlUGEfdmYL-rUWlaa8sVhGqiLi6kO9dAZhKBjwNRY8H5Df7vystqoWJOGGSl6Mn0q9tgse9_SrO6MzNedD", "img_type": "video", "video": "1489355199494292", "win_score": null, "win_type": null, "win_flags": {}}, {"key": "전환_파트너스_미리_플랩", "base_key": "파트너스_미리", "ad_id": "120244300723390667", "objective": "전환", "pa_type": "PA", "landing": "플랩", "purpose": "전환", "mgr": "파트너스", "media": "영상", "spend": 4115, "impressions": 207, "clicks": 4, "purchases": 0, "revenue": 0, "age_days": 76, "roas": 0, "roas_pct": 0, "ctr": 1.93, "cvr": 0.0, "cpc": 1029.0, "is_new": false, "old_roas_pct": null, "roas_delta": null, "prev_spend": 4115, "prev_ctr": 1.93, "prev_cvr": null, "prev_cpc": 1029.0, "prev_purchases": null, "prev_revenue": null, "img": null, "img_type": "video", "video": "1592592422291342", "win_score": null, "win_type": null, "win_flags": {}}, {"key": "전환_26인치_재입고03_세레나_오딧", "base_key": "26인치_재입고03_세레나", "ad_id": "120247323121660667", "objective": "전환", "pa_type": "자컨", "landing": "오딧", "purpose": "전환", "mgr": "세레나", "media": "영상", "spend": 3457, "impressions": 151, "clicks": 2, "purchases": 0, "revenue": 0, "age_days": 23, "roas": 0, "roas_pct": 0, "ctr": 1.32, "cvr": 0.0, "cpc": 1728.0, "is_new": false, "old_roas_pct": null, "roas_delta": null, "prev_spend": 3457, "prev_ctr": 1.32, "prev_cvr": null, "prev_cpc": 1728.0, "prev_purchases": null, "prev_revenue": null, "img": "https://www.facebook.com/ads/image/?d=AQJx8F6RX_qWMwgH_3J3VyOqPQGT8s6cSkkzX1gjduRtSfYiWSE8XDTqS1S90Qu9oJx5r3emk1VXjB6eZqFb_Fj9CjBCWspoKKiXH1rivCyWTAfJcbmaoKfgvLya4nTv7oAqjjs-MZT7N3MasnVrV5KL", "img_type": "video", "video": "1354608403160960", "win_score": null, "win_type": null, "win_flags": {}}, {"key": "전환__hyerimood__수납01_세레나_플랩", "base_key": "_hyerimood__수납01_세레나", "ad_id": "120247091199860667", "objective": "전환", "pa_type": "자컨", "landing": "플랩", "purpose": "전환", "mgr": "세레나", "media": "영상", "spend": 1610, "impressions": 67, "clicks": 3, "purchases": 1.0, "revenue": 401300, "age_days": 31, "roas": 249.254658, "roas_pct": 24925.0, "ctr": 4.48, "cvr": 33.33, "cpc": 537.0, "is_new": false, "old_roas_pct": 24925.0, "roas_delta": 0.0, "prev_spend": 1610, "prev_ctr": 4.48, "prev_cvr": 33.33, "prev_cpc": 537.0, "prev_purchases": 1, "prev_revenue": 401300, "img": "https://scontent-sin2-2.xx.fbcdn.net/v/t45.1600-4/669299467_122117309247225536_8932116954996409745_n.png?stp=dst-jpg_tt6&_nc_cat=103&ccb=1-7&_nc_sid=d5bd00&_nc_ohc=7hmeFcS_iWIQ7kNvwHtYn-K&_nc_oc=AdoYD--anVo7m0M2Ee8ogsS-9dtyNjevFS7hZ3bs44cEX7AmFTNboHi3BlM61AEyjzs&_nc_zt=1&_nc_ht=scontent-sin2-2.xx&edm=AAwGEdEEAAAA&_nc_gid=zL8eVY__tMvel1lP_IB7gg&_nc_tpa=Q5bMBQG3rqQtBdoWng0mNhvXG57gjPUFDCRVDlmZWVaTd5WVW7kMzr2hjumjYm90AsKphx0UbCxXjcOOUg&oh=00_Af-coRk8oa-oY8xUxsX0dC3BwZXYCZ0XJjxXaJwKqVFUzQ&oe=6A36E426", "img_type": "img", "video": null, "win_score": null, "win_type": null, "win_flags": {}}, {"key": "전환__hyerimood__대세감02_세레나_플랩", "base_key": "_hyerimood__대세감02_세레나", "ad_id": "120247091199880667", "objective": "전환", "pa_type": "자컨", "landing": "플랩", "purpose": "전환", "mgr": "세레나", "media": "영상", "spend": 1147, "impressions": 91, "clicks": 2, "purchases": 0, "revenue": 0, "age_days": 31, "roas": 0, "roas_pct": 0, "ctr": 2.2, "cvr": 0.0, "cpc": 574.0, "is_new": false, "old_roas_pct": null, "roas_delta": null, "prev_spend": 1147, "prev_ctr": 2.2, "prev_cvr": null, "prev_cpc": 574.0, "prev_purchases": null, "prev_revenue": null, "img": "https://scontent-sin2-1.xx.fbcdn.net/v/t45.1600-4/668898769_122117309229225536_1738094339845074068_n.png?stp=dst-jpg_tt6&_nc_cat=100&ccb=1-7&_nc_sid=d5bd00&_nc_ohc=GgGxEQPNmLgQ7kNvwEn5RSd&_nc_oc=Adpnzn6qVV024ZCdjkKFOiIeszB5toRRqMDIapMWtUmwbKhGbfj8w2itVDirpOL8tQI&_nc_zt=1&_nc_ht=scontent-sin2-1.xx&edm=AAwGEdEEAAAA&_nc_gid=56d38hr1s8Wh-Ydpcso3Yg&_nc_tpa=Q5bMBQGNyXy_Q-0yTLXrsPgjSgxkcMug0HDk29nxik-r-mZfULd7dr2wPC6jFZNez_mesGUBioJd4lw3Dw&oh=00_Af-6KFPtAtTOfhwh5anHIpy5DpjKbzWqUMvghtt9vvnmgg&oe=6A370703", "img_type": "img", "video": null, "win_score": null, "win_type": null, "win_flags": {}}, {"key": "전환_챈미2차활용_05_세레나_오딧", "base_key": "챈미2차활용_05_세레나", "ad_id": "120247605912540667", "objective": "전환", "pa_type": "자컨", "landing": "오딧", "purpose": "전환", "mgr": "세레나", "media": "영상", "spend": 1108, "impressions": 67, "clicks": 2, "purchases": 2.0, "revenue": 464000, "age_days": 18, "roas": 418.772563, "roas_pct": 41877.0, "ctr": 2.99, "cvr": 100.0, "cpc": 554.0, "is_new": false, "old_roas_pct": 41877.0, "roas_delta": 0.0, "prev_spend": 1108, "prev_ctr": 2.99, "prev_cvr": 100.0, "prev_cpc": 554.0, "prev_purchases": 2, "prev_revenue": 464000, "img": "https://www.facebook.com/ads/image/?d=AQJ-Tfj3CNEPxH5z5JG52awzcMvcOUR417-sN066L0bmETZaeKkiwgtWopKsqJcjQDYNYOlfE6jfiMTihCHTBLCwbzMEmm-0wjwVuUGPqhZCCD6gTYQFzyHitMvGLxPsNCD1sTm-qk1H2BjlxX9N-sXT", "img_type": "video", "video": "949718174523334", "win_score": null, "win_type": null, "win_flags": {}}, {"key": "전환_캐러셀_상시4_콜리_오딧", "base_key": "캐러셀_상시4_콜리", "ad_id": "120242153658590667", "objective": "전환", "pa_type": "자컨", "landing": "오딧", "purpose": "전환", "mgr": "콜리", "media": "영상", "spend": 927, "impressions": 99, "clicks": 1, "purchases": 0, "revenue": 0, "age_days": 138, "roas": 0, "roas_pct": 0, "ctr": 1.01, "cvr": 0.0, "cpc": 927.0, "is_new": false, "old_roas_pct": null, "roas_delta": null, "prev_spend": 927, "prev_ctr": 1.01, "prev_cvr": null, "prev_cpc": 927.0, "prev_purchases": null, "prev_revenue": null, "img": null, "img_type": "img", "video": null, "win_score": null, "win_type": null, "win_flags": {}}, {"key": "전환_5월연휴02_세레나_오딧", "base_key": "5월연휴02_세레나", "ad_id": "120248001875540667", "objective": "전환", "pa_type": "자컨", "landing": "오딧", "purpose": "전환", "mgr": "세레나", "media": "영상", "spend": 745, "impressions": 12, "clicks": 0, "purchases": 0, "revenue": 0, "age_days": 13, "roas": 0, "roas_pct": 0, "ctr": 0.0, "cvr": 0, "cpc": 0, "is_new": false, "old_roas_pct": null, "roas_delta": null, "prev_spend": 745, "prev_ctr": null, "prev_cvr": null, "prev_cpc": null, "prev_purchases": null, "prev_revenue": null, "img": null, "img_type": "img", "video": null, "win_score": null, "win_type": null, "win_flags": {}}, {"key": "전환_1위_세레나_오딧", "base_key": "1위_세레나", "ad_id": "120242867466340667", "objective": "전환", "pa_type": "자컨", "landing": "오딧", "purpose": "전환", "mgr": "세레나", "media": "영상", "spend": 662, "impressions": 17, "clicks": 3, "purchases": 2.0, "revenue": 438465, "age_days": 108, "roas": 662.333837, "roas_pct": 66233.0, "ctr": 17.65, "cvr": 66.67, "cpc": 221.0, "is_new": false, "old_roas_pct": 66233.0, "roas_delta": 0.0, "prev_spend": 662, "prev_ctr": 17.65, "prev_cvr": 66.67, "prev_cpc": 221.0, "prev_purchases": 2, "prev_revenue": 438465, "img": "https://www.facebook.com/ads/image/?d=AQIVMQr331GnyoqOeoFKNtlYdQKIaVFwfGxFQ23YvKYhsJGIuiC22ej8ZYN4By4RTX_A1zKTcVMsFCXHWuuSPGQCZ9rcvz5iX9Zuj2xyhs6dDsnGeEo7jf3XMgazQ4GOxHS5pa_HuhOsb5GvDJaz6wN6", "img_type": "video", "video": "1196352048845155", "win_score": null, "win_type": null, "win_flags": {}}, {"key": "전환_플랩리뷰05_콜리_플랩", "base_key": "플랩리뷰05_콜리", "ad_id": "120247091199890667", "objective": "전환", "pa_type": "자컨", "landing": "플랩", "purpose": "전환", "mgr": "콜리", "media": "영상", "spend": 541, "impressions": 26, "clicks": 0, "purchases": 0, "revenue": 0, "age_days": 31, "roas": 0, "roas_pct": 0, "ctr": 0.0, "cvr": 0, "cpc": 0, "is_new": false, "old_roas_pct": null, "roas_delta": null, "prev_spend": 541, "prev_ctr": null, "prev_cvr": null, "prev_cpc": null, "prev_purchases": null, "prev_revenue": null, "img": "https://www.facebook.com/ads/image/?d=AQKZWbAgqkzRZbdOD8OWe_H57M4ZWYO3VOAN7cClVnyVpwD28ny1I8c8adCNKN-wy-1SjY3Xk-mnE0FxN_k6sEuofQZ6f6P8RNnjcNqTidbG3Ry2T8aySO3FWQsI3Ipf6b3AvuMFFTu_aVMHqLnyz91V", "img_type": "video", "video": "1680246386444483", "win_score": null, "win_type": null, "win_flags": {}}, {"key": "전환_5월연휴04_세레나_오딧", "base_key": "5월연휴04_세레나", "ad_id": "120248001875600667", "objective": "전환", "pa_type": "자컨", "landing": "오딧", "purpose": "전환", "mgr": "세레나", "media": "영상", "spend": 529, "impressions": 19, "clicks": 0, "purchases": 0, "revenue": 0, "age_days": 13, "roas": 0, "roas_pct": 0, "ctr": 0.0, "cvr": 0, "cpc": 0, "is_new": false, "old_roas_pct": null, "roas_delta": null, "prev_spend": 529, "prev_ctr": null, "prev_cvr": null, "prev_cpc": null, "prev_purchases": null, "prev_revenue": null, "img": null, "img_type": "img", "video": null, "win_score": null, "win_type": null, "win_flags": {}}, {"key": "전환_작누댁2차활용_04디벨롭02_세레나_오딧", "base_key": "작누댁2차활용_04디벨롭02_세레나", "ad_id": "120247734527090667", "objective": "전환", "pa_type": "자컨", "landing": "오딧", "purpose": "전환", "mgr": "세레나", "media": "영상", "spend": 528, "impressions": 14, "clicks": 0, "purchases": 0, "revenue": 0, "age_days": 18, "roas": 0, "roas_pct": 0, "ctr": 0.0, "cvr": 0, "cpc": 0, "is_new": false, "old_roas_pct": null, "roas_delta": null, "prev_spend": 528, "prev_ctr": null, "prev_cvr": null, "prev_cpc": null, "prev_purchases": null, "prev_revenue": null, "img": "https://www.facebook.com/ads/image/?d=AQI-CvTmeXPkTu_PCVM6lbzbJ8CqRk6niMgR1GAimat_N56zlFg9FPqmXQ0srP_hO804mbFWO2W-6BRPnO7jIBmQ_1gRRDLeQ3E5xCMw0WoJubpSN8N89gncvyWWfZ-5k-CETR_xbXeZ6HKwmwe_Tfzf", "img_type": "video", "video": "1307369861277210", "win_score": null, "win_type": null, "win_flags": {}}, {"key": "전환_디벨롭01_콜리_오딧", "base_key": "디벨롭01_콜리", "ad_id": "120243237878060667", "objective": "전환", "pa_type": "자컨", "landing": "오딧", "purpose": "전환", "mgr": "콜리", "media": "영상", "spend": 527, "impressions": 29, "clicks": 1, "purchases": 0, "revenue": 0, "age_days": 100, "roas": 0, "roas_pct": 0, "ctr": 3.45, "cvr": 0.0, "cpc": 527.0, "is_new": false, "old_roas_pct": null, "roas_delta": null, "prev_spend": 527, "prev_ctr": 3.45, "prev_cvr": null, "prev_cpc": 527.0, "prev_purchases": null, "prev_revenue": null, "img": "https://www.facebook.com/ads/image/?d=AQJXCveQtwlNy2aYP-kj8UHJ9cQJ93b7eJp90rrJOvTPX_Zq1G_5pD6XVm3ZhccDGpz82WHNIVHTewBEbyiPj0UiKmumdchhrxDA_B_8kLX014xqjKdV1pksgCubyCpe-yTRN_p_lW_qadilYJpPwVcA", "img_type": "video", "video": "877879021832676", "win_score": null, "win_type": null, "win_flags": {}}, {"key": "전환_경사로_03_리지_플랩", "base_key": "경사로_03_리지", "ad_id": "120248233077300667", "objective": "전환", "pa_type": "자컨", "landing": "플랩", "purpose": "전환", "mgr": "리지", "media": "영상", "spend": 25, "impressions": 1, "clicks": 0, "purchases": 0, "revenue": 0, "age_days": 10, "roas": 0, "roas_pct": 0, "ctr": 0.0, "cvr": 0, "cpc": 0, "is_new": false, "old_roas_pct": null, "roas_delta": null, "prev_spend": 25, "prev_ctr": null, "prev_cvr": null, "prev_cpc": null, "prev_purchases": null, "prev_revenue": null, "img": "https://www.facebook.com/ads/image/?d=AQL73QVj1CRr5aPOTK_9V77eoNgTVyKFHyS1jEq-GITVFmcFgzyhPJ-WLnkLwmYmX5zf6e6jRmeqDKnFFeEvvu2-NOLq1YIIFoGVAUYaf8gaKEotsT2smdW5d06kBDnYuqagQLuj5z2nxEN2y8RyhYHr", "img_type": "video", "video": "1516330550100496", "win_score": null, "win_type": null, "win_flags": {}}]}